Workbook

Sheet Productos
A1: id | B1: slug | C1: sku | D1: marca | E1: nombre_original_pt | F1: nombre_es | G1: linea | H1: categoria_original_pt | I1: categoria_es | J1: subcategoria_original_pt | K1: subcategoria_es | L1: tipo_original_pt | M1: tipo_es | N1: presentacion | O1: cantidad | P1: unidad | Q1: precio_regular_brl | R1: precio_oferta_brl | S1: porcentaje_descuento | T1: en_oferta | U1: disponible | V1: descripcion_original_pt | W1: descripcion_es | X1: beneficios_original_pt | Y1: beneficios_es | Z1: propiedades_original_pt | AA1: propiedades_es | AB1: modo_uso_original_pt | AC1: modo_uso_es | AD1: activos_original_pt | AE1: activos_es | AF1: ingredientes_originales | AG1: imagen_principal_url | AH1: imagen_principal_local | AI1: imagenes_adicionales | AJ1: recomendado_para_es | AK1: url_origen | AL1: fecha_extraccion | AM1: precio_regular_pen | AN1: pvp_peru_regular_pen | AO1: precio_oferta_pen | AP1: pvp_peru_oferta_pen
A2: HSK-0001 | B2: tonico-activador-cavalo-forte-120-ml | D2: Haskell | E2: Tonico Ativador Cavalo Forte 120ml | F2: Tonico activador Cavalo Forte 120 ml | G2: Cavalo Forte | H2: Tratamentos Capilares | I2: Tratamientos capilares | J2: Fortalecimento | K2: Fortalecimiento capilar | L2: Tonico | M2: Tonico capilar | N2: 120 ml | O2: 120 | P2: ml | Q2: 56.9 | S2: =IF(ISBLANK(R2),0,IFERROR((Q2-R2)/Q2,0)) | T2: =R2<>"" | U2: =TRUE() | W2: Tonico capilar de la linea Cavalo Forte, formulado para estimular el cuero cabelludo y acompanar el crecimiento saludable del cabello, como parte de una rutina de fortalecimiento. | Y2: Estimula el cuero cabelludo | Contribuye al crecimiento capilar saludable | Fortalece la raiz del cabello | AA2: Fortalecedor | Estimulante del cuero cabelludo | AC2: Aplicar directamente sobre el cuero cabelludo limpio y masajear suavemente. No es necesario enjuagar. | AD2: Biotina | Pantenol | Queratina | AE2: Biotina | Pantenol | Queratina | AH2: tonico-ativador-cavalo-forte-120ml.webp | AJ2: Todo tipo de cabello, especialmente cabello debilitado o con caida | AK2: https://haskellcosmeticos.com.br/tratamentos-capilares/linha-cavalo-forte-haskell/ | AL2: 2026-07-24 | AM2: =IF(ISBLANK(Q2),"",Q2*Parametros_PEN!$B$2) | AN2: =IF(ISBLANK(Q2),"",Q2*Parametros_PEN!$B$2*(1+Parametros_PEN!$B$3)) | AO2: =IF(ISBLANK(R2),"",R2*Parametros_PEN!$B$2) | AP2: =IF(ISBLANK(R2),"",R2*Parametros_PEN!$B$2*(1+Parametros_PEN!$B$3))
A3: HSK-0002 | B3: champu-bendito-loiro-300-ml | D3: Haskell | E3: Shampoo Bendito Loiro 300ml | F3: Champu Bendito Loiro 300 ml | G3: Bendito Loiro | H3: Tratamentos Capilares | I3: Tratamientos capilares | J3: Cabelos descoloridos | K3: Cabello decolorado | L3: Shampoo | M3: Champu | N3: 300 ml | O3: 300 | P3: ml | Q3: 62.9 | S3: =IF(ISBLANK(R3),0,IFERROR((Q3-R3)/Q3,0)) | T3: =R3<>"" | U3: =TRUE() | W3: Champu de limpieza suave de la linea Bendito Loiro, formulado para preparar el cabello decolorado antes del tratamiento, sin agredir la fibra capilar y manteniendo el pH equilibrado. | Y3: Limpieza suave sin agredir los cabellos | Mantiene el pH equilibrado | Evita la rigidez del cabello | AA3: Limpiador suave | pH equilibrado | AC3: Aplicar sobre el cabello mojado, masajear el cuero cabelludo y enjuagar bien. | AD3: Complexo de proteinas | Vinagre balsamico de uva | AE3: Complejo de proteinas | Vinagre balsamico de uva | AH3: shampoo-bendito-loiro-300ml.webp | AJ3: Cabello decolorado o rubio con danos, elasticidad excesiva o porosidad | AK3: https://haskellcosmeticos.com.br/tratamentos-capilares/bendito-loiro/ | AL3: 2026-07-24 | AM3: =IF(ISBLANK(Q3),"",Q3*Parametros_PEN!$B$2) | AN3: =IF(ISBLANK(Q3),"",Q3*Parametros_PEN!$B$2*(1+Parametros_PEN!$B$3)) | AO3: =IF(ISBLANK(R3),"",R3*Parametros_PEN!$B$2) | AP3: =IF(ISBLANK(R3),"",R3*Parametros_PEN!$B$2*(1+Parametros_PEN!$B$3))
A4: HSK-0003 | B4: champu-bendito-loiro-500-ml | D4: Haskell | E4: Shampoo Bendito Loiro 500ml | F4: Champu Bendito Loiro 500 ml | G4: Bendito Loiro | H4: Tratamentos Capilares | I4: Tratamientos capilares | J4: Cabelos descoloridos | K4: Cabello decolorado | L4: Shampoo | M4: Champu | N4: 500 ml | O4: 500 | P4: ml | Q4: 84.9 | S4: =IF(ISBLANK(R4),0,IFERROR((Q4-R4)/Q4,0)) | T4: =R4<>"" | U4: =TRUE() | W4: Champu de limpieza suave de la linea Bendito Loiro, formulado para preparar el cabello decolorado antes del tratamiento, sin agredir la fibra capilar y manteniendo el pH equilibrado. | Y4: Limpieza suave sin agredir los cabellos | Mantiene el pH equilibrado | Evita la rigidez del cabello | AA4: Limpiador suave | pH equilibrado | AC4: Aplicar sobre el cabello mojado, masajear el cuero cabelludo y enjuagar bien. | AD4: Complexo de proteinas | Vinagre balsamico de uva | AE4: Complejo de proteinas | Vinagre balsamico de uva | AH4: shampoo-bendito-loiro-500ml.webp | AJ4: Cabello decolorado o rubio con danos, elasticidad excesiva o porosidad | AK4: https://haskellcosmeticos.com.br/tratamentos-capilares/bendito-loiro/ | AL4: 2026-07-24 | AM4: =IF(ISBLANK(Q4),"",Q4*Parametros_PEN!$B$2) | AN4: =IF(ISBLANK(Q4),"",Q4*Parametros_PEN!$B$2*(1+Parametros_PEN!$B$3)) | AO4: =IF(ISBLANK(R4),"",R4*Parametros_PEN!$B$2) | AP4: =IF(ISBLANK(R4),"",R4*Parametros_PEN!$B$2*(1+Parametros_PEN!$B$3))
A5: HSK-0004 | B5: acondicionador-bendito-loiro-300-ml | D5: Haskell | E5: Condicionador Bendito Loiro 300ml | F5: Acondicionador Bendito Loiro 300 ml | G5: Bendito Loiro | H5: Tratamentos Capilares | I5: Tratamientos capilares | J5: Cabelos descoloridos | K5: Cabello decolorado | L5: Condicionador | M5: Acondicionador | N5: 300 ml | O5: 300 | P5: ml | Q5: 62.9 | S5: =IF(ISBLANK(R5),0,IFERROR((Q5-R5)/Q5,0)) | T5: =R5<>"" | U5: =TRUE() | W5: Acondicionador de la linea Bendito Loiro que sella las cuticulas, repone proteinas y reduce la electricidad estatica del cabello decolorado, aportando suavidad y liviandad. | Y5: Sella las cuticulas | Reduce la electricidad estatica | Repone proteinas | Aporta suavidad y liviandad | AA5: Sellador de cuticulas | Reposicion de proteinas | AC5: Aplicar sobre el cabello lavado, de medios a puntas, dejar actuar unos minutos y enjuagar. | AD5: Complexo de proteinas | Vinagre balsamico de uva | AE5: Complejo de proteinas | Vinagre balsamico de uva | AH5: condicionador-bendito-loiro-300ml.webp | AJ5: Cabello decolorado o rubio con danos, elasticidad excesiva o porosidad | AK5: https://haskellcosmeticos.com.br/tratamentos-capilares/bendito-loiro/ | AL5: 2026-07-24 | AM5: =IF(ISBLANK(Q5),"",Q5*Parametros_PEN!$B$2) | AN5: =IF(ISBLANK(Q5),"",Q5*Parametros_PEN!$B$2*(1+Parametros_PEN!$B$3)) | AO5: =IF(ISBLANK(R5),"",R5*Parametros_PEN!$B$2) | AP5: =IF(ISBLANK(R5),"",R5*Parametros_PEN!$B$2*(1+Parametros_PEN!$B$3))
A6: HSK-0005 | B6: mascarilla-de-tratamiento-bendito-loiro-300-g | D6: Haskell | E6: Mascara de Tratamento Bendito Loiro 300g | F6: Mascarilla de tratamiento Bendito Loiro 300 g | G6: Bendito Loiro | H6: Tratamentos Capilares | I6: Tratamientos capilares | J6: Cabelos descoloridos | K6: Cabello decolorado | L6: Mascara de Tratamento | M6: Mascarilla de tratamiento | N6: 300 g | O6: 300 | P6: g | Q6: 74.9 | S6: =IF(ISBLANK(R6),0,IFERROR((Q6-R6)/Q6,0)) | T6: =R6<>"" | U6: =TRUE() | W6: Mascarilla de alto poder reconstructor de la linea Bendito Loiro, indicada para el tratamiento profundo y la regeneracion de los danos causados por la decoloracion. | Y6: Alto poder reconstructor | Tratamiento profundo | Regenera danos de la decoloracion | AA6: Reconstructora | Regeneradora | AC6: Aplicar sobre el cabello lavado, distribuir de medios a puntas y dejar actuar segun las indicaciones del envase antes de enjuagar. | AD6: Complexo de proteinas | Vinagre balsamico de uva | AE6: Complejo de proteinas | Vinagre balsamico de uva | AH6: mascara-de-tratamento-bendito-loiro-300g.webp | AJ6: Cabello decolorado o rubio con danos, elasticidad excesiva o porosidad | AK6: https://haskellcosmeticos.com.br/tratamentos-capilares/bendito-loiro/ | AL6: 2026-07-24 | AM6: =IF(ISBLANK(Q6),"",Q6*Parametros_PEN!$B$2) | AN6: =IF(ISBLANK(Q6),"",Q6*Parametros_PEN!$B$2*(1+Parametros_PEN!$B$3)) | AO6: =IF(ISBLANK(R6),"",R6*Parametros_PEN!$B$2) | AP6: =IF(ISBLANK(R6),"",R6*Parametros_PEN!$B$2*(1+Parametros_PEN!$B$3))
A7: HSK-0006 | B7: proteina-capilar-bendito-loiro-150-g | D7: Haskell | E7: Proteina Capilar Bendito Loiro 150g | F7: Proteina capilar Bendito Loiro 150 g | G7: Bendito Loiro | H7: Tratamentos Capilares | I7: Tratamientos capilares | J7: Cabelos descoloridos | K7: Cabello decolorado | L7: Reparador | M7: Proteina capilar | N7: 150 g | O7: 150 | P7: g | Q7: 55.9 | S7: =IF(ISBLANK(R7),0,IFERROR((Q7-R7)/Q7,0)) | T7: =R7<>"" | U7: =TRUE() | W7: Pre-champu repositor inmediato de proteina de la linea Bendito Loiro, que reconstruye la estructura interna del cabello y reduce el riesgo de quiebre. | Y7: Reconstruye la estructura interna del cabello | Reduce el riesgo de quiebre | Actua contra la elasticidad excesiva | AA7: Repositor de proteina | Pre-tratamiento | AC7: Aplicar antes del champu, sobre el cabello seco o humedo, siguiendo las indicaciones del envase. | AD7: Complexo de proteinas | AE7: Complejo de proteinas | AH7: proteina-capilar-bendito-loiro-150g.webp | AJ7: Cabello decolorado o rubio con danos, elasticidad excesiva o porosidad | AK7: https://haskellcosmeticos.com.br/tratamentos-capilares/bendito-loiro/ | AL7: 2026-07-24 | AM7: =IF(ISBLANK(Q7),"",Q7*Parametros_PEN!$B$2) | AN7: =IF(ISBLANK(Q7),"",Q7*Parametros_PEN!$B$2*(1+Parametros_PEN!$B$3)) | AO7: =IF(ISBLANK(R7),"",R7*Parametros_PEN!$B$2) | AP7: =IF(ISBLANK(R7),"",R7*Parametros_PEN!$B$2*(1+Parametros_PEN!$B$3))
A8: HSK-0007 | B8: fluido-proteico-bendito-loiro-120-ml | D8: Haskell | E8: Fluido Proteico Bendito Loiro 120ml | F8: Fluido proteico Bendito Loiro 120 ml | G8: Bendito Loiro | H8: Tratamentos Capilares | I8: Tratamientos capilares | J8: Cabelos descoloridos | K8: Cabello decolorado | L8: Finalizador | M8: Fluido finalizador | N8: 120 ml | O8: 120 | P8: ml | Q8: 48.9 | S8: =IF(ISBLANK(R8),0,IFERROR((Q8-R8)/Q8,0)) | T8: =R8<>"" | U8: =TRUE() | W8: Fluido finalizador de la linea Bendito Loiro que aporta luminosidad, accion antifrizz y proteccion termica y solar al cabello decolorado. | Y8: Aporta luminosidad | Accion antifrizz | Proteccion termica y solar | AA8: Finalizador | Protector termico | AC8: Aplicar una pequena cantidad sobre el cabello humedo o seco, de medios a puntas, antes de peinar o usar herramientas de calor. | AD8: Complexo de proteinas | Vinagre balsamico de uva | AE8: Complejo de proteinas | Vinagre balsamico de uva | AH8: fluido-proteico-bendito-loiro-120ml.webp | AJ8: Cabello decolorado o rubio con danos, elasticidad excesiva o porosidad | AK8: https://haskellcosmeticos.com.br/tratamentos-capilares/bendito-loiro/ | AL8: 2026-07-24 | AM8: =IF(ISBLANK(Q8),"",Q8*Parametros_PEN!$B$2) | AN8: =IF(ISBLANK(Q8),"",Q8*Parametros_PEN!$B$2*(1+Parametros_PEN!$B$3)) | AO8: =IF(ISBLANK(R8),"",R8*Parametros_PEN!$B$2) | AP8: =IF(ISBLANK(R8),"",R8*Parametros_PEN!$B$2*(1+Parametros_PEN!$B$3))
A9: HSK-0008 | B9: champu-de-uso-diario-matcha-y-romero-300-ml | D9: Haskell | E9: Shampoo Uso Diario Matcha & Alecrim 300ml | F9: Champu de uso diario Matcha y romero 300 ml | G9: Matcha | H9: Tratamentos Capilares | I9: Tratamientos capilares | J9: Controle da oleosidade | K9: Control de la grasitud capilar | L9: Shampoo | M9: Champu | N9: 300 ml | O9: 300 | P9: ml | Q9: 58.9 | S9: =IF(ISBLANK(R9),0,IFERROR((Q9-R9)/Q9,0)) | T9: =R9<>"" | U9: =TRUE() | W9: Champu de uso diario de la linea Matcha, formulado con matcha y romero para controlar la grasitud del cuero cabelludo y mantener el cabello limpio y liviano por mas tiempo. | Y9: Controla la grasitud del cuero cabelludo | Fortalece los cabellos desde la raiz | Mantiene la limpieza por mas tiempo | AA9: Anti-grasitud | Limpieza diaria | AC9: Aplicar sobre el cabello mojado, masajear el cuero cabelludo y enjuagar. Puede usarse a diario. | AD9: Matcha | Extrato de Alecrim | AE9: Matcha | Extracto de romero | AH9: shampoo-uso-diario-matcha-alecrim-300ml.webp | AJ9: Cabello graso o con tendencia a la grasitud excesiva | AK9: https://haskellcosmeticos.com.br/tratamentos-capilares/linha-matcha-haskell/ | AL9: 2026-07-24 | AM9: =IF(ISBLANK(Q9),"",Q9*Parametros_PEN!$B$2) | AN9: =IF(ISBLANK(Q9),"",Q9*Parametros_PEN!$B$2*(1+Parametros_PEN!$B$3)) | AO9: =IF(ISBLANK(R9),"",R9*Parametros_PEN!$B$2) | AP9: =IF(ISBLANK(R9),"",R9*Parametros_PEN!$B$2*(1+Parametros_PEN!$B$3))
A10: HSK-0009 | B10: champu-antirresiduos-matcha-y-menta-300-ml | D10: Haskell | E10: Shampoo Antirresiduos Matcha & Hortela 300ml | F10: Champu antirresiduos Matcha y menta 300 ml | G10: Matcha | H10: Tratamentos Capilares | I10: Tratamientos capilares | J10: Controle da oleosidade | K10: Control de la grasitud capilar | L10: Shampoo | M10: Champu | N10: 300 ml | O10: 300 | P10: ml | Q10: 58.9 | S10: =IF(ISBLANK(R10),0,IFERROR((Q10-R10)/Q10,0)) | T10: =R10<>"" | U10: =TRUE() | W10: Champu de limpieza profunda de la linea Matcha, formulado con matcha y menta para eliminar residuos de productos de peinado y contaminacion, y prevenir la caida del cabello. | Y10: Limpieza profunda | Elimina residuos de productos y contaminacion | Previene la caida del cabello | Sensacion de frescor | AA10: Limpieza profunda | Efecto refrescante | AC10: Aplicar sobre el cabello mojado, masajear el cuero cabelludo y enjuagar bien. Se recomienda su uso periodico, no necesariamente a diario. | AD10: Matcha | Extrato de Hortela | AE10: Matcha | Extracto de menta | AH10: shampoo-antirresiduos-matcha-hortela-300ml.webp | AJ10: Cabello graso o con acumulacion de residuos de productos | AK10: https://haskellcosmeticos.com.br/tratamentos-capilares/linha-matcha-haskell/ | AL10: 2026-07-24 | AM10: =IF(ISBLANK(Q10),"",Q10*Parametros_PEN!$B$2) | AN10: =IF(ISBLANK(Q10),"",Q10*Parametros_PEN!$B$2*(1+Parametros_PEN!$B$3)) | AO10: =IF(ISBLANK(R10),"",R10*Parametros_PEN!$B$2) | AP10: =IF(ISBLANK(R10),"",R10*Parametros_PEN!$B$2*(1+Parametros_PEN!$B$3))
A11: HSK-0010 | B11: acondicionador-matcha-y-romero-300-ml | D11: Haskell | E11: Condicionador Matcha & Alecrim 300ml | F11: Acondicionador Matcha y romero 300 ml | G11: Matcha | H11: Tratamentos Capilares | I11: Tratamientos capilares | J11: Controle da oleosidade | K11: Control de la grasitud capilar | L11: Condicionador | M11: Acondicionador | N11: 300 ml | O11: 300 | P11: ml | Q11: 58.9 | S11: =IF(ISBLANK(R11),0,IFERROR((Q11-R11)/Q11,0)) | T11: =R11<>"" | U11: =TRUE() | W11: Acondicionador liviano de la linea Matcha que protege el cabello sin sobrecargarlo, ayuda a prevenir la caida y evita el resecamiento de las puntas. | Y11: Condiciona sin sobrecargar el cabello | Ayuda a prevenir la caida | Evita el resecamiento de las puntas | AA11: Liviano | No sobrecarga el cabello | AC11: Aplicar sobre el cabello lavado, de medios a puntas, dejar actuar y enjuagar. | AD11: Matcha | Extrato de Alecrim | AE11: Matcha | Extracto de romero | AH11: condicionador-matcha-alecrim-300ml.webp | AJ11: Cabello graso o con tendencia a la grasitud excesiva | AK11: https://haskellcosmeticos.com.br/tratamentos-capilares/linha-matcha-haskell/ | AL11: 2026-07-24 | AM11: =IF(ISBLANK(Q11),"",Q11*Parametros_PEN!$B$2) | AN11: =IF(ISBLANK(Q11),"",Q11*Parametros_PEN!$B$2*(1+Parametros_PEN!$B$3)) | AO11: =IF(ISBLANK(R11),"",R11*Parametros_PEN!$B$2) | AP11: =IF(ISBLANK(R11),"",R11*Parametros_PEN!$B$2*(1+Parametros_PEN!$B$3))
A12: HSK-0011 | B12: fluido-revitalizante-matcha-y-romero-120-ml | D12: Haskell | E12: Fluido Revitalizante Matcha & Alecrim 120ml | F12: Fluido revitalizante Matcha y romero 120 ml | G12: Matcha | H12: Tratamentos Capilares | I12: Tratamientos capilares | J12: Controle da oleosidade | K12: Control de la grasitud capilar | L12: Finalizador | M12: Fluido finalizador | N12: 120 ml | O12: 120 | P12: ml | Q12: 48.9 | S12: =IF(ISBLANK(R12),0,IFERROR((Q12-R12)/Q12,0)) | T12: =R12<>"" | U12: =TRUE() | W12: Fluido liviano y de rapida absorcion de la linea Matcha, que protege la fibra capilar frente a agresores externos y aporta luminosidad adicional. | Y12: Absorcion rapida | Protege la fibra capilar | Aporta luminosidad adicional | AA12: Liviano | Facil absorcion | AC12: Aplicar una pequena cantidad sobre el cabello humedo o seco, evitando la raiz si el cabello es graso. | AD12: Matcha | Extrato de Alecrim | AE12: Matcha | Extracto de romero | AH12: fluido-revitalizante-matcha-alecrim-120ml.webp | AJ12: Cabello graso o con tendencia a la grasitud excesiva | AK12: https://haskellcosmeticos.com.br/tratamentos-capilares/linha-matcha-haskell/ | AL12: 2026-07-24 | AM12: =IF(ISBLANK(Q12),"",Q12*Parametros_PEN!$B$2) | AN12: =IF(ISBLANK(Q12),"",Q12*Parametros_PEN!$B$2*(1+Parametros_PEN!$B$3)) | AO12: =IF(ISBLANK(R12),"",R12*Parametros_PEN!$B$2) | AP12: =IF(ISBLANK(R12),"",R12*Parametros_PEN!$B$2*(1+Parametros_PEN!$B$3))
A13: HSK-0012 | B13: champu-murumuru-300-ml | D13: Haskell | E13: Shampoo Murumuru 300ml | F13: Champu Murumuru 300 ml | G13: Murumuru | H13: Tratamentos Capilares | I13: Tratamientos capilares | J13: Nutricao intensa | K13: Nutricion intensa | L13: Shampoo | M13: Champu | N13: 300 ml | O13: 300 | P13: ml | Q13: 58.9 | S13: =IF(ISBLANK(R13),0,IFERROR((Q13-R13)/Q13,0)) | T13: =R13<>"" | U13: =TRUE() | W13: Champu de la linea Murumuru que realiza una limpieza suave y repone nutrientes y vitaminas esenciales, indicado para cabello muy seco. | Y13: Limpieza suave | Repone nutrientes y vitaminas esenciales | AA13: Nutritivo | Limpieza suave | AC13: Aplicar sobre el cabello mojado, masajear el cuero cabelludo y enjuagar bien. | AD13: Manteiga de Murumuru | AE13: Manteca de murumuru | AH13: shampoo-murumuru-300ml.webp | AJ13: Cabello muy seco, opaco o deshidratado | AK13: https://haskellcosmeticos.com.br/tratamentos-capilares/linha-murumuru-haskell/ | AL13: 2026-07-24 | AM13: =IF(ISBLANK(Q13),"",Q13*Parametros_PEN!$B$2) | AN13: =IF(ISBLANK(Q13),"",Q13*Parametros_PEN!$B$2*(1+Parametros_PEN!$B$3)) | AO13: =IF(ISBLANK(R13),"",R13*Parametros_PEN!$B$2) | AP13: =IF(ISBLANK(R13),"",R13*Parametros_PEN!$B$2*(1+Parametros_PEN!$B$3))
A14: HSK-0013 | B14: champu-murumuru-500-ml | D14: Haskell | E14: Shampoo Murumuru 500ml | F14: Champu Murumuru 500 ml | G14: Murumuru | H14: Tratamentos Capilares | I14: Tratamientos capilares | J14: Nutricao intensa | K14: Nutricion intensa | L14: Shampoo | M14: Champu | N14: 500 ml | O14: 500 | P14: ml | Q14: 76.9 | S14: =IF(ISBLANK(R14),0,IFERROR((Q14-R14)/Q14,0)) | T14: =R14<>"" | U14: =TRUE() | W14: Champu de la linea Murumuru que realiza una limpieza suave y repone nutrientes y vitaminas esenciales, indicado para cabello muy seco. | Y14: Limpieza suave | Repone nutrientes y vitaminas esenciales | AA14: Nutritivo | Limpieza suave | AC14: Aplicar sobre el cabello mojado, masajear el cuero cabelludo y enjuagar bien. | AD14: Manteiga de Murumuru | AE14: Manteca de murumuru | AH14: shampoo-murumuru-haskell-500ml.webp | AJ14: Cabello muy seco, opaco o deshidratado | AK14: https://haskellcosmeticos.com.br/tratamentos-capilares/linha-murumuru-haskell/ | AL14: 2026-07-24 | AM14: =IF(ISBLANK(Q14),"",Q14*Parametros_PEN!$B$2) | AN14: =IF(ISBLANK(Q14),"",Q14*Parametros_PEN!$B$2*(1+Parametros_PEN!$B$3)) | AO14: =IF(ISBLANK(R14),"",R14*Parametros_PEN!$B$2) | AP14: =IF(ISBLANK(R14),"",R14*Parametros_PEN!$B$2*(1+Parametros_PEN!$B$3))
A15: HSK-0014 | B15: fluido-alineador-frizz-cancelado-200-ml | D15: Haskell | E15: Fluido Alinhador Frizz Cancelado 200ml | F15: Fluido alineador Frizz Cancelado 200 ml | G15: Frizz Cancelado | H15: Tratamentos Capilares | I15: Tratamientos capilares | J15: Controle de frizz | K15: Control del frizz | L15: Finalizador | M15: Fluido finalizador | N15: 200 ml | O15: 200 | P15: ml | Q15: 59.9 | S15: =IF(ISBLANK(R15),0,IFERROR((Q15-R15)/Q15,0)) | T15: =R15<>"" | U15: =TRUE() | W15: Fluido finalizador de la linea Frizz Cancelado que ayuda a alinear y disciplinar el cabello, dejandolo con brillo intenso durante todo el dia sin apelmazarlo. | Y15: Alinea y disciplina el cabello | Brillo intenso durante todo el dia | No apelmaza el cabello | AA15: Alineador | Antifrizz | AC15: Aplicar sobre el cabello humedo o seco, de medios a puntas, antes de peinar. | AE15: No especificado en la pagina de linea (pendiente de confirmar en ficha de producto) | AH15: fluido-alinhador-frizz-cancelado-200ml.webp | AI15: fluido-alinhador-frizz-cancelado-200ml_02.webp | AJ15: Cabello con frizz | AK15: https://haskellcosmeticos.com.br/tratamentos-capilares/frizz-cancelado/ | AL15: 2026-07-24 | AM15: =IF(ISBLANK(Q15),"",Q15*Parametros_PEN!$B$2) | AN15: =IF(ISBLANK(Q15),"",Q15*Parametros_PEN!$B$2*(1+Parametros_PEN!$B$3)) | AO15: =IF(ISBLANK(R15),"",R15*Parametros_PEN!$B$2) | AP15: =IF(ISBLANK(R15),"",R15*Parametros_PEN!$B$2*(1+Parametros_PEN!$B$3))
A16: HSK-0015 | B16: aceite-blindaje-capilar-frizz-cancelado-100-ml | D16: Haskell | E16: Oleo Blinda Fio Frizz Cancelado 100ml | F16: Aceite blindaje capilar Frizz Cancelado 100 ml | G16: Frizz Cancelado | H16: Tratamentos Capilares | I16: Tratamientos capilares | J16: Controle de frizz | K16: Control del frizz | L16: Reparador | M16: Aceite capilar | N16: 100 ml | O16: 100 | P16: ml | Q16: 95.9 | S16: =IF(ISBLANK(R16),0,IFERROR((Q16-R16)/Q16,0)) | T16: =R16<>"" | U16: =TRUE() | W16: Aceite capilar de la linea Frizz Cancelado, formulado para proteger la fibra capilar y contribuir al control del frizz, dejando el cabello con brillo. | Y16: Protege la fibra capilar | Contribuye al control del frizz | Aporta brillo | AA16: Protector | Antifrizz | AC16: Aplicar pocas gotas sobre el cabello humedo o seco, de medios a puntas. | AE16: No especificado en la pagina de linea (pendiente de confirmar en ficha de producto) | AH16: oleo-blinda-fio-frizz-cancelado-100ml.webp | AI16: oleo-blinda-fio-frizz-cancelado-100ml_02.webp | AJ16: Cabello con frizz | AK16: https://haskellcosmeticos.com.br/tratamentos-capilares/frizz-cancelado/ | AL16: 2026-07-24 | AM16: =IF(ISBLANK(Q16),"",Q16*Parametros_PEN!$B$2) | AN16: =IF(ISBLANK(Q16),"",Q16*Parametros_PEN!$B$2*(1+Parametros_PEN!$B$3)) | AO16: =IF(ISBLANK(R16),"",R16*Parametros_PEN!$B$2) | AP16: =IF(ISBLANK(R16),"",R16*Parametros_PEN!$B$2*(1+Parametros_PEN!$B$3))
A17: HSK-0016 | B17: mascarilla-liquida-lamelar-frizz-cancelado-200-ml | D17: Haskell | E17: Mascara Liquida Lamelar Frizz Cancelado 200ml | F17: Mascarilla liquida lamelar Frizz Cancelado 200 ml | G17: Frizz Cancelado | H17: Tratamentos Capilares | I17: Tratamientos capilares | J17: Controle de frizz | K17: Control del frizz | L17: Mascara Liquida Lamelar | M17: Mascarilla liquida lamelar | N17: 200 ml | O17: 200 | P17: ml | Q17: 81.9 | S17: =IF(ISBLANK(R17),0,IFERROR((Q17-R17)/Q17,0)) | T17: =R17<>"" | U17: =TRUE() | W17: Mascarilla liquida de tecnologia lamelar de la linea Frizz Cancelado, que ayuda a alinear el cabello y controlar el frizz con un acabado liviano. | Y17: Alinea el cabello | Controla el frizz | Acabado liviano | AA17: Tecnologia lamelar | Antifrizz | AC17: Aplicar sobre el cabello lavado, distribuir de medios a puntas y enjuagar segun las indicaciones del envase. | AE17: No especificado en la pagina de linea (pendiente de confirmar en ficha de producto) | AH17: mascara-liquida-lamelar-frizz-cancelado-200ml.webp | AI17: mascara-liquida-lamelar-frizz-cancelado-200ml_02.webp | AJ17: Cabello con frizz | AK17: https://haskellcosmeticos.com.br/tratamentos-capilares/frizz-cancelado/ | AL17: 2026-07-24 | AM17: =IF(ISBLANK(Q17),"",Q17*Parametros_PEN!$B$2) | AN17: =IF(ISBLANK(Q17),"",Q17*Parametros_PEN!$B$2*(1+Parametros_PEN!$B$3)) | AO17: =IF(ISBLANK(R17),"",R17*Parametros_PEN!$B$2) | AP17: =IF(ISBLANK(R17),"",R17*Parametros_PEN!$B$2*(1+Parametros_PEN!$B$3))
A18: HSK-0017 | B18: champu-cachos-si-300-ml | D18: Haskell | E18: Shampoo Cachos Sim! 300ml | F18: Champu Cachos Si! 300 ml | G18: Cachos Sim! | H18: Tratamentos Capilares | I18: Tratamientos capilares | J18: Cuidado de cachos | K18: Cuidado de rizos | L18: Shampoo | M18: Champu | N18: 300 ml | O18: 300 | P18: ml | Q18: 62.9 | S18: =IF(ISBLANK(R18),0,IFERROR((Q18-R18)/Q18,0)) | T18: =R18<>"" | U18: =TRUE() | W18: Champu de la linea Cachos Si!, formulado sin sulfatos, petrolatos ni parabenos (tecnica low poo), que limpia suavemente sin remover los aceites naturales del cabello rizado. | Y18: Limpieza suave sin remover aceites naturales | Hidrata el cabello y el cuero cabelludo | Libre de sulfatos, petrolatos y parabenos | AA18: Formula low poo | Libre de sulfatos | AC18: Aplicar sobre el cabello mojado, masajear el cuero cabelludo y enjuagar bien. | AD18: Oleo de Coco | Colageno Vegetal | AE18: Aceite de coco | Colageno vegetal | AH18: shampoo-cachos-sim-haskell-300ml.webp | AJ18: Cabello rizado y ondulado | AK18: https://haskellcosmeticos.com.br/tratamentos-capilares/linha-cachos-sim-haskell/ | AL18: 2026-07-24 | AM18: =IF(ISBLANK(Q18),"",Q18*Parametros_PEN!$B$2) | AN18: =IF(ISBLANK(Q18),"",Q18*Parametros_PEN!$B$2*(1+Parametros_PEN!$B$3)) | AO18: =IF(ISBLANK(R18),"",R18*Parametros_PEN!$B$2) | AP18: =IF(ISBLANK(R18),"",R18*Parametros_PEN!$B$2*(1+Parametros_PEN!$B$3))
A19: HSK-0018 | B19: acondicionador-cachos-si-300-ml | D19: Haskell | E19: Condicionador Cachos Sim! 300ml | F19: Acondicionador Cachos Si! 300 ml | G19: Cachos Sim! | H19: Tratamentos Capilares | I19: Tratamientos capilares | J19: Cuidado de cachos | K19: Cuidado de rizos | L19: Condicionador | M19: Acondicionador | N19: 300 ml | O19: 300 | P19: ml | Q19: 62.9 | S19: =IF(ISBLANK(R19),0,IFERROR((Q19-R19)/Q19,0)) | T19: =R19<>"" | U19: =TRUE() | W19: Acondicionador de la linea Cachos Si! que aporta emoliencia, definicion y brillo, ayuda a controlar el frizz y favorece el cierre de las cuticulas. | Y19: Aporta emoliencia, definicion y brillo | Controla el frizz | Favorece el cierre de las cuticulas | Reduce el volumen | AA19: Emoliente | Definidor de rizos | AC19: Aplicar sobre el cabello lavado, de medios a puntas, dejar actuar y enjuagar. | AD19: Oleo de Coco | Colageno Vegetal | AE19: Aceite de coco | Colageno vegetal | AH19: condicionador-cachos-sim-haskell-300ml.webp | AJ19: Cabello rizado y ondulado | AK19: https://haskellcosmeticos.com.br/tratamentos-capilares/linha-cachos-sim-haskell/ | AL19: 2026-07-24 | AM19: =IF(ISBLANK(Q19),"",Q19*Parametros_PEN!$B$2) | AN19: =IF(ISBLANK(Q19),"",Q19*Parametros_PEN!$B$2*(1+Parametros_PEN!$B$3)) | AO19: =IF(ISBLANK(R19),"",R19*Parametros_PEN!$B$2) | AP19: =IF(ISBLANK(R19),"",R19*Parametros_PEN!$B$2*(1+Parametros_PEN!$B$3))
A20: HSK-0019 | B20: mascarilla-humectante-cachos-si-300-g | D20: Haskell | E20: Mascara Umectante Cachos Sim! 300g | F20: Mascarilla humectante Cachos Si! 300 g | G20: Cachos Sim! | H20: Tratamentos Capilares | I20: Tratamientos capilares | J20: Cuidado de cachos | K20: Cuidado de rizos | L20: Mascara de Tratamento | M20: Mascarilla de tratamiento | N20: 300 g | O20: 300 | P20: g | Q20: 74.9 | S20: =IF(ISBLANK(R20),0,IFERROR((Q20-R20)/Q20,0)) | T20: =R20<>"" | U20: =TRUE() | W20: Mascarilla altamente humectante de la linea Cachos Si!, que devuelve la humedad natural, nutre los rizos mas secos y realza su forma original. | Y20: Alto poder humectante | Nutre los rizos mas secos | Realza la forma original del rizo | AA20: Humectante | Nutritiva | AC20: Aplicar sobre el cabello lavado, distribuir de medios a puntas y dejar actuar antes de enjuagar. | AD20: Oleo de Coco | Colageno Vegetal | AE20: Aceite de coco | Colageno vegetal | AH20: mascara-umectante-cachos-sim-300g.webp | AJ20: Cabello rizado y ondulado, especialmente el mas seco | AK20: https://haskellcosmeticos.com.br/tratamentos-capilares/linha-cachos-sim-haskell/ | AL20: 2026-07-24 | AM20: =IF(ISBLANK(Q20),"",Q20*Parametros_PEN!$B$2) | AN20: =IF(ISBLANK(Q20),"",Q20*Parametros_PEN!$B$2*(1+Parametros_PEN!$B$3)) | AO20: =IF(ISBLANK(R20),"",R20*Parametros_PEN!$B$2) | AP20: =IF(ISBLANK(R20),"",R20*Parametros_PEN!$B$2*(1+Parametros_PEN!$B$3))
A21: HSK-0020 | B21: leave-in-memorizador-de-rizos-cachos-si-300-ml | D21: Haskell | E21: Leave In Memorizador de Cachos Cachos Sim! 300ml | F21: Leave-in memorizador de rizos Cachos Si! 300 ml | G21: Cachos Sim! | H21: Tratamentos Capilares | I21: Tratamientos capilares | J21: Cuidado de cachos | K21: Cuidado de rizos | L21: Finalizador | M21: Leave-in (sin enjuague) | N21: 300 ml | O21: 300 | P21: ml | Q21: 68.9 | S21: =IF(ISBLANK(R21),0,IFERROR((Q21-R21)/Q21,0)) | T21: =R21<>"" | U21: =TRUE() | W21: Leave-in de la linea Cachos Si! que activa y define los rizos, controla el frizz y reactiva la memoria del cabello, con proteccion solar y termica. | Y21: Activa y define los rizos | Controla el frizz | Reactiva la memoria del rizo | Proteccion solar y termica | AA21: Definidor | Con proteccion termica y solar | AC21: Aplicar sobre el cabello humedo, distribuir mechon por mechon y dejar secar al aire o con difusor. | AD21: Oleo de Coco | Colageno Vegetal | AE21: Aceite de coco | Colageno vegetal | AH21: leave-in-memorizador-de-cachos-cachos-sim-haskell-300ml.webp | AJ21: Cabello rizado y ondulado | AK21: https://haskellcosmeticos.com.br/tratamentos-capilares/linha-cachos-sim-haskell/ | AL21: 2026-07-24 | AM21: =IF(ISBLANK(Q21),"",Q21*Parametros_PEN!$B$2) | AN21: =IF(ISBLANK(Q21),"",Q21*Parametros_PEN!$B$2*(1+Parametros_PEN!$B$3)) | AO21: =IF(ISBLANK(R21),"",R21*Parametros_PEN!$B$2) | AP21: =IF(ISBLANK(R21),"",R21*Parametros_PEN!$B$2*(1+Parametros_PEN!$B$3))
A22: HSK-0021 | B22: supermascarilla-acidificante-reductora-de-ph-240-g | D22: Haskell | E22: Supermascara Acidificante Redutor de pH 240g | F22: Supermascarilla acidificante reductora de pH 240 g | G22: Acidificante | H22: Tratamentos Capilares | I22: Tratamientos capilares | J22: Reconstrucao pos-quimica | K22: Reconstruccion post-quimica | L22: Mascara de Tratamento | M22: Mascarilla de tratamiento | N22: 240 g | O22: 240 | P22: g | Q22: 74.9 | S22: =IF(ISBLANK(R22),0,IFERROR((Q22-R22)/Q22,0)) | T22: =R22<>"" | U22: =TRUE() | W22: Mascarilla de tratamiento concentrada de la linea Acidificante, de uso posterior al champu: ayuda a reconstruir el cabello danado por procesos quimicos y a equilibrar el pH de los hilos. | Y22: Tratamiento concentrado | Actua en profundidad sobre la fibra capilar | Refuerza el resultado de la linea | AA22: Tratamiento intensivo | AC22: Aplicar mechon por mechon despues del champu, dejar actuar de 3 a 5 minutos y enjuagar bien. | AD22: Blend de vinagres | Arginina | AE22: Blend de vinagres | Arginina | AH22: supermascara-acidificante-redutor-de-ph-240g.webp | AJ22: Cabello danado por procesos quimicos, con porosidad alta | AK22: https://haskellcosmeticos.com.br/tratamentos-capilares/linha-acidificante-haskell/ | AL22: 2026-07-24 | AM22: =IF(ISBLANK(Q22),"",Q22*Parametros_PEN!$B$2) | AN22: =IF(ISBLANK(Q22),"",Q22*Parametros_PEN!$B$2*(1+Parametros_PEN!$B$3)) | AO22: =IF(ISBLANK(R22),"",R22*Parametros_PEN!$B$2) | AP22: =IF(ISBLANK(R22),"",R22*Parametros_PEN!$B$2*(1+Parametros_PEN!$B$3))
A23: HSK-0022 | B23: champu-acidificante-300-ml | D23: Haskell | E23: Shampoo Acidificante 300ml | F23: Champu acidificante 300 ml | G23: Acidificante | H23: Tratamentos Capilares | I23: Tratamientos capilares | J23: Reconstrucao pos-quimica | K23: Reconstruccion post-quimica | L23: Shampoo | M23: Champu | N23: 300 ml | O23: 300 | P23: ml | Q23: 62.9 | S23: =IF(ISBLANK(R23),0,IFERROR((Q23-R23)/Q23,0)) | T23: =R23<>"" | U23: =TRUE() | W23: Champu de limpieza suave de la linea Acidificante, que prepara el cabello para el tratamiento: ayuda a reconstruir el cabello danado por procesos quimicos y a equilibrar el pH de los hilos. | Y23: Limpieza suave sin resecar | Prepara el cabello para el resto de la rutina | Respeta el equilibrio del cuero cabelludo | AA23: Limpiador suave | AC23: Aplicar sobre el cabello mojado, masajear el cuero cabelludo con movimientos suaves y enjuagar bien. | AD23: Blend de vinagres | Arginina | AE23: Blend de vinagres | Arginina | AH23: shampoo-acidificante-300ml.webp | AJ23: Cabello danado por procesos quimicos, con porosidad alta | AK23: https://haskellcosmeticos.com.br/tratamentos-capilares/linha-acidificante-haskell/ | AL23: 2026-07-24 | AM23: =IF(ISBLANK(Q23),"",Q23*Parametros_PEN!$B$2) | AN23: =IF(ISBLANK(Q23),"",Q23*Parametros_PEN!$B$2*(1+Parametros_PEN!$B$3)) | AO23: =IF(ISBLANK(R23),"",R23*Parametros_PEN!$B$2) | AP23: =IF(ISBLANK(R23),"",R23*Parametros_PEN!$B$2*(1+Parametros_PEN!$B$3))
A24: HSK-0023 | B24: fluido-reconstructor-acidificante-200-ml | D24: Haskell | E24: Fluido Reconstrutor Acidificante 200ml | F24: Fluido reconstructor acidificante 200 ml | G24: Acidificante | H24: Tratamentos Capilares | I24: Tratamientos capilares | J24: Reconstrucao pos-quimica | K24: Reconstruccion post-quimica | L24: Fluido | M24: Fluido finalizador | N24: 200 ml | O24: 200 | P24: ml | Q24: 59.9 | S24: =IF(ISBLANK(R24),0,IFERROR((Q24-R24)/Q24,0)) | T24: =R24<>"" | U24: =TRUE() | W24: Fluido finalizador sin enjuague de la linea Acidificante: ayuda a reconstruir el cabello danado por procesos quimicos y a equilibrar el pH de los hilos. | Y24: Finalizador sin enjuague | Facilita el peinado | Protege del calor y de agresiones externas | AA24: Finalizador | AC24: Aplicar sobre el cabello limpio y humedo, distribuir en todo el largo y finalizar como se prefiera. | AD24: Blend de vinagres | Arginina | AE24: Blend de vinagres | Arginina | AH24: fluido-reconstrutor-acidificante-200ml.webp | AJ24: Cabello danado por procesos quimicos, con porosidad alta | AK24: https://haskellcosmeticos.com.br/tratamentos-capilares/linha-acidificante-haskell/ | AL24: 2026-07-24 | AM24: =IF(ISBLANK(Q24),"",Q24*Parametros_PEN!$B$2) | AN24: =IF(ISBLANK(Q24),"",Q24*Parametros_PEN!$B$2*(1+Parametros_PEN!$B$3)) | AO24: =IF(ISBLANK(R24),"",R24*Parametros_PEN!$B$2) | AP24: =IF(ISBLANK(R24),"",R24*Parametros_PEN!$B$2*(1+Parametros_PEN!$B$3))
A25: HSK-0024 | B25: supermascarilla-acidificante-matizadora-240-g | D25: Haskell | E25: Supermascara Acidificante Matizadora 240g | F25: Supermascarilla acidificante matizadora 240 g | G25: Acidificante Matizadora | H25: Tratamentos Capilares | I25: Tratamientos capilares | J25: Matizacao acida | K25: Matizacion acida para cabello rubio o canoso | L25: Mascara de Tratamento | M25: Mascarilla de tratamiento | N25: 240 g | O25: 240 | P25: g | Q25: 74.9 | S25: =IF(ISBLANK(R25),0,IFERROR((Q25-R25)/Q25,0)) | T25: =R25<>"" | U25: =TRUE() | W25: Mascarilla de tratamiento concentrada de la linea Acidificante Matizadora, de uso posterior al champu: neutraliza el tono amarillento y equilibra el pH del cabello rubio, decolorado o canoso. | Y25: Tratamiento concentrado | Actua en profundidad sobre la fibra capilar | Refuerza el resultado de la linea | AA25: Tratamiento intensivo | AC25: Aplicar mechon por mechon despues del champu, dejar actuar de 3 a 5 minutos y enjuagar bien. | AD25: Blend de vinagres | Arginina | AE25: Blend de vinagres | Arginina | AH25: Supermascarilla acidificante matizadora 240 g.webp | AJ25: Cabello rubio, decolorado o canoso con tono amarillento | AK25: https://haskellcosmeticos.com.br/tratamentos-capilares/acidificante-matizadora/ | AL25: 2026-07-24 | AM25: =IF(ISBLANK(Q25),"",Q25*Parametros_PEN!$B$2) | AN25: =IF(ISBLANK(Q25),"",Q25*Parametros_PEN!$B$2*(1+Parametros_PEN!$B$3)) | AO25: =IF(ISBLANK(R25),"",R25*Parametros_PEN!$B$2) | AP25: =IF(ISBLANK(R25),"",R25*Parametros_PEN!$B$2*(1+Parametros_PEN!$B$3))
A26: HSK-0025 | B26: champu-acidificante-matizador-300-ml | D26: Haskell | E26: Shampoo Acidificante Matizador 300ml | F26: Champu acidificante matizador 300 ml | G26: Acidificante Matizadora | H26: Tratamentos Capilares | I26: Tratamientos capilares | J26: Matizacao acida | K26: Matizacion acida para cabello rubio o canoso | L26: Shampoo | M26: Champu | N26: 300 ml | O26: 300 | P26: ml | Q26: 62.9 | S26: =IF(ISBLANK(R26),0,IFERROR((Q26-R26)/Q26,0)) | T26: =R26<>"" | U26: =TRUE() | W26: Champu de limpieza suave de la linea Acidificante Matizadora, que prepara el cabello para el tratamiento: neutraliza el tono amarillento y equilibra el pH del cabello rubio, decolorado o canoso. | Y26: Limpieza suave sin resecar | Prepara el cabello para el resto de la rutina | Respeta el equilibrio del cuero cabelludo | AA26: Limpiador suave | AC26: Aplicar sobre el cabello mojado, masajear el cuero cabelludo con movimientos suaves y enjuagar bien. | AD26: Blend de vinagres | Arginina | AE26: Blend de vinagres | Arginina | AH26: shampoo-acidificante-matizador-300ml.webp | AI26: shampoo-acidificante-matizador-300ml_02.webp | AJ26: Cabello rubio, decolorado o canoso con tono amarillento | AK26: https://haskellcosmeticos.com.br/tratamentos-capilares/acidificante-matizadora/ | AL26: 2026-07-24 | AM26: =IF(ISBLANK(Q26),"",Q26*Parametros_PEN!$B$2) | AN26: =IF(ISBLANK(Q26),"",Q26*Parametros_PEN!$B$2*(1+Parametros_PEN!$B$3)) | AO26: =IF(ISBLANK(R26),"",R26*Parametros_PEN!$B$2) | AP26: =IF(ISBLANK(R26),"",R26*Parametros_PEN!$B$2*(1+Parametros_PEN!$B$3))
A27: HSK-0026 | B27: balsamo-cicatrizante-acidificante-matizador-100-ml | D27: Haskell | E27: Balm Cicatrizante Acidificante Matizador 100ml | F27: Balsamo cicatrizante acidificante matizador 100 ml | G27: Acidificante Matizadora | H27: Tratamentos Capilares | I27: Tratamientos capilares | J27: Matizacao acida | K27: Matizacion acida para cabello rubio o canoso | L27: Balm | M27: Balsamo | N27: 100 ml | O27: 100 | P27: ml | Q27: 95.9 | S27: =IF(ISBLANK(R27),0,IFERROR((Q27-R27)/Q27,0)) | T27: =R27<>"" | U27: =TRUE() | W27: Balsamo de accion reparadora de la linea Acidificante Matizadora: neutraliza el tono amarillento y equilibra el pH del cabello rubio, decolorado o canoso. | Y27: Accion reparadora localizada | Complementa el tratamiento de la linea | AA27: Balsamo tratante | AC27: Aplicar sobre el cabello segun las indicaciones del envase, como parte de la rutina de la linea. | AD27: Blend de vinagres | Arginina | AE27: Blend de vinagres | Arginina | AH27: balm-cicatrizante-acidificante-matizador-100ml.webp | AI27: balm-cicatrizante-acidificante-matizador-100ml_02.webp | AJ27: Cabello rubio, decolorado o canoso con tono amarillento | AK27: https://haskellcosmeticos.com.br/tratamentos-capilares/acidificante-matizadora/ | AL27: 2026-07-24 | AM27: =IF(ISBLANK(Q27),"",Q27*Parametros_PEN!$B$2) | AN27: =IF(ISBLANK(Q27),"",Q27*Parametros_PEN!$B$2*(1+Parametros_PEN!$B$3)) | AO27: =IF(ISBLANK(R27),"",R27*Parametros_PEN!$B$2) | AP27: =IF(ISBLANK(R27),"",R27*Parametros_PEN!$B$2*(1+Parametros_PEN!$B$3))
A28: HSK-0027 | B28: champu-amatista-desamarilladora-300-ml | D28: Haskell | E28: Shampoo Ametista Desamareladora 300ml | F28: Champu amatista desamarilladora 300 ml | G28: Ametista Desamareladora | H28: Tratamentos Capilares | I28: Tratamientos capilares | J28: Desamarelamento gradual | K28: Desamarillamiento gradual | L28: Shampoo | M28: Champu | N28: 300 ml | O28: 300 | P28: ml | Q28: 62.9 | S28: =IF(ISBLANK(R28),0,IFERROR((Q28-R28)/Q28,0)) | T28: =R28<>"" | U28: =TRUE() | W28: Champu de limpieza suave de la linea Ametista Desamareladora, que prepara el cabello para el tratamiento: neutraliza de forma gradual los reflejos amarillentos y aporta brillo. | Y28: Limpieza suave sin resecar | Prepara el cabello para el resto de la rutina | Respeta el equilibrio del cuero cabelludo | AA28: Limpiador suave | AC28: Aplicar sobre el cabello mojado, masajear el cuero cabelludo con movimientos suaves y enjuagar bien. | AD28: Ametista (mineral) | Blend de aminoacidos | AE28: Amatista (mineral) | Blend de aminoacidos | AH28: shampoo-ametista-desamareladora-300ml.webp | AJ28: Cabello rubio, decolorado, canoso o cabello oscuro que necesita mas brillo | AK28: https://haskellcosmeticos.com.br/tratamentos-capilares/linha-ametista-haskell/ | AL28: 2026-07-24 | AM28: =IF(ISBLANK(Q28),"",Q28*Parametros_PEN!$B$2) | AN28: =IF(ISBLANK(Q28),"",Q28*Parametros_PEN!$B$2*(1+Parametros_PEN!$B$3)) | AO28: =IF(ISBLANK(R28),"",R28*Parametros_PEN!$B$2) | AP28: =IF(ISBLANK(R28),"",R28*Parametros_PEN!$B$2*(1+Parametros_PEN!$B$3))
A29: HSK-0028 | B29: acondicionador-amatista-desamarilladora-300-ml | D29: Haskell | E29: Condicionador Ametista Desamareladora 300ml | F29: Acondicionador amatista desamarilladora 300 ml | G29: Ametista Desamareladora | H29: Tratamentos Capilares | I29: Tratamientos capilares | J29: Desamarelamento gradual | K29: Desamarillamiento gradual | L29: Condicionador | M29: Acondicionador | N29: 300 ml | O29: 300 | P29: ml | Q29: 62.9 | S29: =IF(ISBLANK(R29),0,IFERROR((Q29-R29)/Q29,0)) | T29: =R29<>"" | U29: =TRUE() | W29: Acondicionador de la linea Ametista Desamareladora que facilita el desenredado y sella la cuticula: neutraliza de forma gradual los reflejos amarillentos y aporta brillo. | Y29: Facilita el desenredado | Sella la cuticula | Aporta suavidad y brillo | AA29: Acondicionador | AC29: Aplicar en el largo y las puntas del cabello despues del champu, dejar actuar unos minutos y enjuagar. | AD29: Ametista (mineral) | Blend de aminoacidos | AE29: Amatista (mineral) | Blend de aminoacidos | AH29: condicionador-ametista-desamareladora-300ml.webp | AJ29: Cabello rubio, decolorado, canoso o cabello oscuro que necesita mas brillo | AK29: https://haskellcosmeticos.com.br/tratamentos-capilares/linha-ametista-haskell/ | AL29: 2026-07-24 | AM29: =IF(ISBLANK(Q29),"",Q29*Parametros_PEN!$B$2) | AN29: =IF(ISBLANK(Q29),"",Q29*Parametros_PEN!$B$2*(1+Parametros_PEN!$B$3)) | AO29: =IF(ISBLANK(R29),"",R29*Parametros_PEN!$B$2) | AP29: =IF(ISBLANK(R29),"",R29*Parametros_PEN!$B$2*(1+Parametros_PEN!$B$3))
A30: HSK-0029 | B30: mascarilla-de-tratamiento-amatista-desamarilladora-300-g | D30: Haskell | E30: Mascara de Tratamento Ametista Desamareladora 300g | F30: Mascarilla de tratamiento amatista desamarilladora 300 g | G30: Ametista Desamareladora | H30: Tratamentos Capilares | I30: Tratamientos capilares | J30: Desamarelamento gradual | K30: Desamarillamiento gradual | L30: Mascara de Tratamento | M30: Mascarilla de tratamiento | N30: 300 g | O30: 300 | P30: g | Q30: 74.9 | S30: =IF(ISBLANK(R30),0,IFERROR((Q30-R30)/Q30,0)) | T30: =R30<>"" | U30: =TRUE() | W30: Mascarilla de tratamiento concentrada de la linea Ametista Desamareladora, de uso posterior al champu: neutraliza de forma gradual los reflejos amarillentos y aporta brillo. | Y30: Tratamiento concentrado | Actua en profundidad sobre la fibra capilar | Refuerza el resultado de la linea | AA30: Tratamiento intensivo | AC30: Aplicar mechon por mechon despues del champu, dejar actuar de 3 a 5 minutos y enjuagar bien. | AD30: Ametista (mineral) | Blend de aminoacidos | AE30: Amatista (mineral) | Blend de aminoacidos | AH30: mascara-de-tratamento-ametista-desamareladora-300g.webp | AJ30: Cabello rubio, decolorado, canoso o cabello oscuro que necesita mas brillo | AK30: https://haskellcosmeticos.com.br/tratamentos-capilares/linha-ametista-haskell/ | AL30: 2026-07-24 | AM30: =IF(ISBLANK(Q30),"",Q30*Parametros_PEN!$B$2) | AN30: =IF(ISBLANK(Q30),"",Q30*Parametros_PEN!$B$2*(1+Parametros_PEN!$B$3)) | AO30: =IF(ISBLANK(R30),"",R30*Parametros_PEN!$B$2) | AP30: =IF(ISBLANK(R30),"",R30*Parametros_PEN!$B$2*(1+Parametros_PEN!$B$3))
A31: HSK-0030 | B31: fluido-iluminador-amatista-desamarilladora-120-ml | D31: Haskell | E31: Fluido Iluminador Ametista Desamareladora 120ml | F31: Fluido iluminador amatista desamarilladora 120 ml | G31: Ametista Desamareladora | H31: Tratamentos Capilares | I31: Tratamientos capilares | J31: Desamarelamento gradual | K31: Desamarillamiento gradual | L31: Fluido | M31: Fluido finalizador | N31: 120 ml | O31: 120 | P31: ml | Q31: 48.9 | S31: =IF(ISBLANK(R31),0,IFERROR((Q31-R31)/Q31,0)) | T31: =R31<>"" | U31: =TRUE() | W31: Fluido finalizador sin enjuague de la linea Ametista Desamareladora: neutraliza de forma gradual los reflejos amarillentos y aporta brillo. | Y31: Finalizador sin enjuague | Facilita el peinado | Protege del calor y de agresiones externas | AA31: Finalizador | AC31: Aplicar sobre el cabello limpio y humedo, distribuir en todo el largo y finalizar como se prefiera. | AD31: Ametista (mineral) | Blend de aminoacidos | AE31: Amatista (mineral) | Blend de aminoacidos | AH31: fluido-iluminador-ametista-desamareladora-120ml.webp | AJ31: Cabello rubio, decolorado, canoso o cabello oscuro que necesita mas brillo | AK31: https://haskellcosmeticos.com.br/tratamentos-capilares/linha-ametista-haskell/ | AL31: 2026-07-24 | AM31: =IF(ISBLANK(Q31),"",Q31*Parametros_PEN!$B$2) | AN31: =IF(ISBLANK(Q31),"",Q31*Parametros_PEN!$B$2*(1+Parametros_PEN!$B$3)) | AO31: =IF(ISBLANK(R31),"",R31*Parametros_PEN!$B$2) | AP31: =IF(ISBLANK(R31),"",R31*Parametros_PEN!$B$2*(1+Parametros_PEN!$B$3))
A32: HSK-0031 | B32: champu-bananeira-posquimica-300-ml | D32: Haskell | E32: Shampoo Bananeira Pos-Quimica 300ml | F32: Champu Bananeira Posquimica 300 ml | G32: Bananeira Pos-Quimica | H32: Tratamentos Capilares | I32: Tratamientos capilares | J32: Reposicao de massa pos-quimica | K32: Reposicion de masa capilar post-quimica | L32: Shampoo | M32: Champu | N32: 300 ml | O32: 300 | P32: ml | Q32: 62.9 | S32: =IF(ISBLANK(R32),0,IFERROR((Q32-R32)/Q32,0)) | T32: =R32<>"" | U32: =TRUE() | W32: Champu de limpieza suave de la linea Bananeira Pos-Quimica, que prepara el cabello para el tratamiento: repone la masa capilar perdida en procesos quimicos y ayuda a reducir la quiebre. | Y32: Limpieza suave sin resecar | Prepara el cabello para el resto de la rutina | Respeta el equilibrio del cuero cabelludo | AA32: Limpiador suave | AC32: Aplicar sobre el cabello mojado, masajear el cuero cabelludo con movimientos suaves y enjuagar bien. | AD32: Nutrientes de banana | Oleo de pequi | AE32: Nutrientes de platano (banana) | Aceite de pequi | AH32: shampoo-bananeira-pos-quimica-300ml.webp | AJ32: Cabello danado por alisados, tinturas o decoloracion | AK32: https://haskellcosmeticos.com.br/tratamentos-capilares/linha-bananeira-haskell/ | AL32: 2026-07-24 | AM32: =IF(ISBLANK(Q32),"",Q32*Parametros_PEN!$B$2) | AN32: =IF(ISBLANK(Q32),"",Q32*Parametros_PEN!$B$2*(1+Parametros_PEN!$B$3)) | AO32: =IF(ISBLANK(R32),"",R32*Parametros_PEN!$B$2) | AP32: =IF(ISBLANK(R32),"",R32*Parametros_PEN!$B$2*(1+Parametros_PEN!$B$3))
A33: HSK-0032 | B33: champu-bananeira-posquimica-500-ml | D33: Haskell | E33: Shampoo Bananeira Pos Quimica 500ml | F33: Champu Bananeira Posquimica 500 ml | G33: Bananeira Pos-Quimica | H33: Tratamentos Capilares | I33: Tratamientos capilares | J33: Reposicao de massa pos-quimica | K33: Reposicion de masa capilar post-quimica | L33: Shampoo | M33: Champu | N33: 500 ml | O33: 500 | P33: ml | Q33: 84.9 | S33: =IF(ISBLANK(R33),0,IFERROR((Q33-R33)/Q33,0)) | T33: =R33<>"" | U33: =TRUE() | W33: Champu de limpieza suave de la linea Bananeira Pos-Quimica, que prepara el cabello para el tratamiento: repone la masa capilar perdida en procesos quimicos y ayuda a reducir la quiebre. | Y33: Limpieza suave sin resecar | Prepara el cabello para el resto de la rutina | Respeta el equilibrio del cuero cabelludo | AA33: Limpiador suave | AC33: Aplicar sobre el cabello mojado, masajear el cuero cabelludo con movimientos suaves y enjuagar bien. | AD33: Nutrientes de banana | Oleo de pequi | AE33: Nutrientes de platano (banana) | Aceite de pequi | AH33: shampoo-bananeira-pos-quimica-500ml.webp | AJ33: Cabello danado por alisados, tinturas o decoloracion | AK33: https://haskellcosmeticos.com.br/tratamentos-capilares/linha-bananeira-haskell/ | AL33: 2026-07-24 | AM33: =IF(ISBLANK(Q33),"",Q33*Parametros_PEN!$B$2) | AN33: =IF(ISBLANK(Q33),"",Q33*Parametros_PEN!$B$2*(1+Parametros_PEN!$B$3)) | AO33: =IF(ISBLANK(R33),"",R33*Parametros_PEN!$B$2) | AP33: =IF(ISBLANK(R33),"",R33*Parametros_PEN!$B$2*(1+Parametros_PEN!$B$3))
A34: HSK-0033 | B34: acondicionador-bananeira-posquimica-300-ml | D34: Haskell | E34: Condicionador Bananeira Pos-Quimica 300ml | F34: Acondicionador Bananeira Posquimica 300 ml | G34: Bananeira Pos-Quimica | H34: Tratamentos Capilares | I34: Tratamientos capilares | J34: Reposicao de massa pos-quimica | K34: Reposicion de masa capilar post-quimica | L34: Condicionador | M34: Acondicionador | N34: 300 ml | O34: 300 | P34: ml | Q34: 62.9 | S34: =IF(ISBLANK(R34),0,IFERROR((Q34-R34)/Q34,0)) | T34: =R34<>"" | U34: =TRUE() | W34: Acondicionador de la linea Bananeira Pos-Quimica que facilita el desenredado y sella la cuticula: repone la masa capilar perdida en procesos quimicos y ayuda a reducir la quiebre. | Y34: Facilita el desenredado | Sella la cuticula | Aporta suavidad y brillo | AA34: Acondicionador | AC34: Aplicar en el largo y las puntas del cabello despues del champu, dejar actuar unos minutos y enjuagar. | AD34: Nutrientes de banana | Oleo de pequi | AE34: Nutrientes de platano (banana) | Aceite de pequi | AH34: condicionador-bananeira-pos-quimica-300ml.webp | AJ34: Cabello danado por alisados, tinturas o decoloracion | AK34: https://haskellcosmeticos.com.br/tratamentos-capilares/linha-bananeira-haskell/ | AL34: 2026-07-24 | AM34: =IF(ISBLANK(Q34),"",Q34*Parametros_PEN!$B$2) | AN34: =IF(ISBLANK(Q34),"",Q34*Parametros_PEN!$B$2*(1+Parametros_PEN!$B$3)) | AO34: =IF(ISBLANK(R34),"",R34*Parametros_PEN!$B$2) | AP34: =IF(ISBLANK(R34),"",R34*Parametros_PEN!$B$2*(1+Parametros_PEN!$B$3))
A35: HSK-0034 | B35: acondicionador-bananeira-posquimica-500-ml | D35: Haskell | E35: Condicionador Bananeira Pos Quimica 500ml | F35: Acondicionador Bananeira Posquimica 500 ml | G35: Bananeira Pos-Quimica | H35: Tratamentos Capilares | I35: Tratamientos capilares | J35: Reposicao de massa pos-quimica | K35: Reposicion de masa capilar post-quimica | L35: Condicionador | M35: Acondicionador | N35: 500 ml | O35: 500 | P35: ml | Q35: 84.9 | S35: =IF(ISBLANK(R35),0,IFERROR((Q35-R35)/Q35,0)) | T35: =R35<>"" | U35: =TRUE() | W35: Acondicionador de la linea Bananeira Pos-Quimica que facilita el desenredado y sella la cuticula: repone la masa capilar perdida en procesos quimicos y ayuda a reducir la quiebre. | Y35: Facilita el desenredado | Sella la cuticula | Aporta suavidad y brillo | AA35: Acondicionador | AC35: Aplicar en el largo y las puntas del cabello despues del champu, dejar actuar unos minutos y enjuagar. | AD35: Nutrientes de banana | Oleo de pequi | AE35: Nutrientes de platano (banana) | Aceite de pequi | AH35: condicionador-bananeira-pos-quimica-500ml.webp | AJ35: Cabello danado por alisados, tinturas o decoloracion | AK35: https://haskellcosmeticos.com.br/tratamentos-capilares/linha-bananeira-haskell/ | AL35: 2026-07-24 | AM35: =IF(ISBLANK(Q35),"",Q35*Parametros_PEN!$B$2) | AN35: =IF(ISBLANK(Q35),"",Q35*Parametros_PEN!$B$2*(1+Parametros_PEN!$B$3)) | AO35: =IF(ISBLANK(R35),"",R35*Parametros_PEN!$B$2) | AP35: =IF(ISBLANK(R35),"",R35*Parametros_PEN!$B$2*(1+Parametros_PEN!$B$3))
A36: HSK-0035 | B36: mascarilla-de-tratamiento-bananeira-posquimica-300-g | D36: Haskell | E36: Mascara de Tratamento Bananeira Pos-Quimica 300g | F36: Mascarilla de tratamiento Bananeira Posquimica 300 g | G36: Bananeira Pos-Quimica | H36: Tratamentos Capilares | I36: Tratamientos capilares | J36: Reposicao de massa pos-quimica | K36: Reposicion de masa capilar post-quimica | L36: Mascara de Tratamento | M36: Mascarilla de tratamiento | N36: 300 g | O36: 300 | P36: g | Q36: 74.9 | S36: =IF(ISBLANK(R36),0,IFERROR((Q36-R36)/Q36,0)) | T36: =R36<>"" | U36: =TRUE() | W36: Mascarilla de tratamiento concentrada de la linea Bananeira Pos-Quimica, de uso posterior al champu: repone la masa capilar perdida en procesos quimicos y ayuda a reducir la quiebre. | Y36: Tratamiento concentrado | Actua en profundidad sobre la fibra capilar | Refuerza el resultado de la linea | AA36: Tratamiento intensivo | AC36: Aplicar mechon por mechon despues del champu, dejar actuar de 3 a 5 minutos y enjuagar bien. | AD36: Nutrientes de banana | Oleo de pequi | AE36: Nutrientes de platano (banana) | Aceite de pequi | AH36: mascara-de-tratamento-bananeira-pos-quimica-300g.webp | AJ36: Cabello danado por alisados, tinturas o decoloracion | AK36: https://haskellcosmeticos.com.br/tratamentos-capilares/linha-bananeira-haskell/ | AL36: 2026-07-24 | AM36: =IF(ISBLANK(Q36),"",Q36*Parametros_PEN!$B$2) | AN36: =IF(ISBLANK(Q36),"",Q36*Parametros_PEN!$B$2*(1+Parametros_PEN!$B$3)) | AO36: =IF(ISBLANK(R36),"",R36*Parametros_PEN!$B$2) | AP36: =IF(ISBLANK(R36),"",R36*Parametros_PEN!$B$2*(1+Parametros_PEN!$B$3))
A37: HSK-0036 | B37: mascarilla-de-tratamiento-bananeira-posquimica-500-g | D37: Haskell | E37: Mascara de Tratamento Bananeira Pos-Quimica 500g | F37: Mascarilla de tratamiento Bananeira Posquimica 500 g | G37: Bananeira Pos-Quimica | H37: Tratamentos Capilares | I37: Tratamientos capilares | J37: Reposicao de massa pos-quimica | K37: Reposicion de masa capilar post-quimica | L37: Mascara de Tratamento | M37: Mascarilla de tratamiento | N37: 500 g | O37: 500 | P37: g | Q37: 89.9 | S37: =IF(ISBLANK(R37),0,IFERROR((Q37-R37)/Q37,0)) | T37: =R37<>"" | U37: =TRUE() | W37: Mascarilla de tratamiento concentrada de la linea Bananeira Pos-Quimica, de uso posterior al champu: repone la masa capilar perdida en procesos quimicos y ayuda a reducir la quiebre. | Y37: Tratamiento concentrado | Actua en profundidad sobre la fibra capilar | Refuerza el resultado de la linea | AA37: Tratamiento intensivo | AC37: Aplicar mechon por mechon despues del champu, dejar actuar de 3 a 5 minutos y enjuagar bien. | AD37: Nutrientes de banana | Oleo de pequi | AE37: Nutrientes de platano (banana) | Aceite de pequi | AH37: mascara-de-tratamento-bananeira-pos-quimica-500g.webp | AJ37: Cabello danado por alisados, tinturas o decoloracion | AK37: https://haskellcosmeticos.com.br/tratamentos-capilares/linha-bananeira-haskell/ | AL37: 2026-07-24 | AM37: =IF(ISBLANK(Q37),"",Q37*Parametros_PEN!$B$2) | AN37: =IF(ISBLANK(Q37),"",Q37*Parametros_PEN!$B$2*(1+Parametros_PEN!$B$3)) | AO37: =IF(ISBLANK(R37),"",R37*Parametros_PEN!$B$2) | AP37: =IF(ISBLANK(R37),"",R37*Parametros_PEN!$B$2*(1+Parametros_PEN!$B$3))
A38: HSK-0037 | B38: fluido-obligatorio-bananeira-posquimica-120-ml | D38: Haskell | E38: Fluido Obrigatorio Bananeira Pos-Quimica 120ml | F38: Fluido obligatorio Bananeira Posquimica 120 ml | G38: Bananeira Pos-Quimica | H38: Tratamentos Capilares | I38: Tratamientos capilares | J38: Reposicao de massa pos-quimica | K38: Reposicion de masa capilar post-quimica | L38: Fluido | M38: Fluido finalizador | N38: 120 ml | O38: 120 | P38: ml | Q38: 48.9 | S38: =IF(ISBLANK(R38),0,IFERROR((Q38-R38)/Q38,0)) | T38: =R38<>"" | U38: =TRUE() | W38: Fluido finalizador sin enjuague de la linea Bananeira Pos-Quimica: repone la masa capilar perdida en procesos quimicos y ayuda a reducir la quiebre. | Y38: Finalizador sin enjuague | Facilita el peinado | Protege del calor y de agresiones externas | AA38: Finalizador | AC38: Aplicar sobre el cabello limpio y humedo, distribuir en todo el largo y finalizar como se prefiera. | AD38: Nutrientes de banana | Oleo de pequi | AE38: Nutrientes de platano (banana) | Aceite de pequi | AH38: fluido-obrigatorio-bananeira-pos-quimica-120ml.webp | AJ38: Cabello danado por alisados, tinturas o decoloracion | AK38: https://haskellcosmeticos.com.br/tratamentos-capilares/linha-bananeira-haskell/ | AL38: 2026-07-24 | AM38: =IF(ISBLANK(Q38),"",Q38*Parametros_PEN!$B$2) | AN38: =IF(ISBLANK(Q38),"",Q38*Parametros_PEN!$B$2*(1+Parametros_PEN!$B$3)) | AO38: =IF(ISBLANK(R38),"",R38*Parametros_PEN!$B$2) | AP38: =IF(ISBLANK(R38),"",R38*Parametros_PEN!$B$2*(1+Parametros_PEN!$B$3))
A39: HSK-0038 | B39: nectavita-bananeira-posquimica-35-ml | D39: Haskell | E39: Nectavita Bananeira Pos-Quimica 35ml | F39: Nectavita Bananeira Posquimica 35 ml | G39: Bananeira Pos-Quimica | H39: Tratamentos Capilares | I39: Tratamientos capilares | J39: Reposicao de massa pos-quimica | K39: Reposicion de masa capilar post-quimica | L39: Nectavita | M39: Potenciador pre-champu | N39: 35 ml | O39: 35 | P39: ml | Q39: 25.9 | S39: =IF(ISBLANK(R39),0,IFERROR((Q39-R39)/Q39,0)) | T39: =R39<>"" | U39: =TRUE() | W39: Potenciador pre-champu (nectavita) de la linea Bananeira Pos-Quimica, para usar antes del lavado: repone la masa capilar perdida en procesos quimicos y ayuda a reducir la quiebre. | Y39: Prepara el cuero cabelludo antes del champu | Potencia el efecto del tratamiento | AA39: Pre-champu | AC39: Aplicar sobre el cuero cabelludo antes del champu, masajear y proceder con el lavado habitual. | AD39: Nutrientes de banana | Oleo de pequi | AE39: Nutrientes de platano (banana) | Aceite de pequi | AH39: nectavita-bananeira-pos-quimica-35ml.webp | AJ39: Cabello danado por alisados, tinturas o decoloracion | AK39: https://haskellcosmeticos.com.br/tratamentos-capilares/linha-bananeira-haskell/ | AL39: 2026-07-24 | AM39: =IF(ISBLANK(Q39),"",Q39*Parametros_PEN!$B$2) | AN39: =IF(ISBLANK(Q39),"",Q39*Parametros_PEN!$B$2*(1+Parametros_PEN!$B$3)) | AO39: =IF(ISBLANK(R39),"",R39*Parametros_PEN!$B$2) | AP39: =IF(ISBLANK(R39),"",R39*Parametros_PEN!$B$2*(1+Parametros_PEN!$B$3))
... A46: HSK-0045 | B46: fluido-hidratante-cavalo-forte-hidra-120-ml | D46: Haskell | E46: Fluido Hidratante Cavalo Forte Hidra 120ml | F46: Fluido hidratante Cavalo Forte Hidra 120 ml | G46: Cavalo Forte Hidra | H46: Tratamentos Capilares | I46: Tratamientos capilares | J46: Hidratacao profunda | K46: Hidratacion profunda | L46: Fluido | M46: Fluido finalizador | N46: 120 ml | O46: 120 | P46: ml | Q46: 48.9 | S46: =IF(ISBLANK(R46),0,IFERROR((Q46-R46)/Q46,0)) | T46: =R46<>"" | U46: =TRUE() | W46: Fluido finalizador sin enjuague de la linea Cavalo Forte Hidra: aporta hidratacion profunda y protege el cabello frente a agresiones externas. | Y46: Finalizador sin enjuague | Facilita el peinado | Protege del calor y de agresiones externas | AA46: Finalizador | AC46: Aplicar sobre el cabello limpio y humedo, distribuir en todo el largo y finalizar como se prefiera. | AD46: Acido hialuronico | Oleo de rosa mosqueta | Vitamina B3 | AE46: Acido hialuronico | Aceite de rosa mosqueta | Vitamina B3 | AH46: fluido-hidratante-cavalo-forte-hidra-120ml.webp | AJ46: Todo tipo de cabello, especialmente cabello reseco | AK46: https://haskellcosmeticos.com.br/tratamentos-capilares/cavalo-forte-hidra/ | AL46: 2026-07-24 | AM46: =IF(ISBLANK(Q46),"",Q46*Parametros_PEN!$B$2) | AN46: =IF(ISBLANK(Q46),"",Q46*Parametros_PEN!$B$2*(1+Parametros_PEN!$B$3)) | AO46: =IF(ISBLANK(R46),"",R46*Parametros_PEN!$B$2) | AP46: =IF(ISBLANK(R46),"",R46*Parametros_PEN!$B$2*(1+Parametros_PEN!$B$3))
A47: HSK-0046 | B47: exfoliante-corporal-doce-de-leite-150-g | D47: Haskell | E47: Esfoliante Corporal Doce de Leite 150g | F47: Exfoliante corporal Doce de Leite 150 g | G47: Doce de Leite Vicosa | H47: Tratamentos Capilares | I47: Tratamientos capilares | J47: Colecao corpo e cabelo perfumada | K47: Coleccion de cuidado corporal y capilar perfumada | L47: Esfoliante | M47: Exfoliante corporal | N47: 150 g | O47: 150 | P47: g | Q47: 43.9 | S47: =IF(ISBLANK(R47),0,IFERROR((Q47-R47)/Q47,0)) | T47: =R47<>"" | U47: =TRUE() | W47: Exfoliante corporal de la coleccion Doce de Leite Vicosa: cuida el cabello y la piel con una fragancia dulce, dentro de una coleccion especial de la marca. | Y47: Elimina celulas muertas | Deja la piel suave | Fragancia de la coleccion | AA47: Exfoliante corporal | AC47: Aplicar sobre la piel humeda, masajear con movimientos circulares y enjuagar. | AD47: Leite vegetal | Pantenol | AE47: Leche vegetal | Pantenol | AH47: esfoliante-corporal-doce-de-leite-150g.webp | AI47: esfoliante-corporal-doce-de-leite-150g_02.webp | AJ47: Quienes buscan una rutina de cuidado perfumada para cabello y piel | AK47: https://haskellcosmeticos.com.br/tratamentos-capilares/doce-de-leite-vicosa/ | AL47: 2026-07-24 | AM47: =IF(ISBLANK(Q47),"",Q47*Parametros_PEN!$B$2) | AN47: =IF(ISBLANK(Q47),"",Q47*Parametros_PEN!$B$2*(1+Parametros_PEN!$B$3)) | AO47: =IF(ISBLANK(R47),"",R47*Parametros_PEN!$B$2) | AP47: =IF(ISBLANK(R47),"",R47*Parametros_PEN!$B$2*(1+Parametros_PEN!$B$3))
A48: HSK-0047 | B48: balsamo-labial-hidratante-doce-de-leite-10-g | D48: Haskell | E48: Hidratante Labial Doce de Leite 10g | F48: Balsamo labial hidratante Doce de Leite 10 g | G48: Doce de Leite Vicosa | H48: Tratamentos Capilares | I48: Tratamientos capilares | J48: Colecao corpo e cabelo perfumada | K48: Coleccion de cuidado corporal y capilar perfumada | L48: Hidratante Labial | M48: Balsamo labial | N48: 10 g | O48: 10 | P48: g | Q48: 25.9 | S48: =IF(ISBLANK(R48),0,IFERROR((Q48-R48)/Q48,0)) | T48: =R48<>"" | U48: =TRUE() | W48: Balsamo labial de la coleccion Doce de Leite Vicosa: cuida el cabello y la piel con una fragancia dulce, dentro de una coleccion especial de la marca. | Y48: Hidrata los labios | Efecto gloss | Fragancia de la coleccion | AA48: Balsamo labial | AC48: Aplicar directamente sobre los labios cuantas veces sea necesario. | AD48: Leite vegetal | Pantenol | AE48: Leche vegetal | Pantenol | AH48: hidratante-labial-doce-de-leite-10g.webp | AI48: hidratante-labial-doce-de-leite-10g_02.webp | AJ48: Quienes buscan una rutina de cuidado perfumada para cabello y piel | AK48: https://haskellcosmeticos.com.br/tratamentos-capilares/doce-de-leite-vicosa/ | AL48: 2026-07-24 | AM48: =IF(ISBLANK(Q48),"",Q48*Parametros_PEN!$B$2) | AN48: =IF(ISBLANK(Q48),"",Q48*Parametros_PEN!$B$2*(1+Parametros_PEN!$B$3)) | AO48: =IF(ISBLANK(R48),"",R48*Parametros_PEN!$B$2) | AP48: =IF(ISBLANK(R48),"",R48*Parametros_PEN!$B$2*(1+Parametros_PEN!$B$3))
A49: HSK-0048 | B49: champu-doce-de-leite-300-ml | D49: Haskell | E49: Shampoo Doce de Leite 300ml | F49: Champu Doce de Leite 300 ml | G49: Doce de Leite Vicosa | H49: Tratamentos Capilares | I49: Tratamientos capilares | J49: Colecao corpo e cabelo perfumada | K49: Coleccion de cuidado corporal y capilar perfumada | L49: Shampoo | M49: Champu | N49: 300 ml | O49: 300 | P49: ml | Q49: 62.9 | S49: =IF(ISBLANK(R49),0,IFERROR((Q49-R49)/Q49,0)) | T49: =R49<>"" | U49: =TRUE() | W49: Champu de limpieza suave de la linea Doce de Leite Vicosa, que prepara el cabello para el tratamiento: cuida el cabello y la piel con una fragancia dulce, dentro de una coleccion especial de la marca. | Y49: Limpieza suave sin resecar | Prepara el cabello para el resto de la rutina | Respeta el equilibrio del cuero cabelludo | AA49: Limpiador suave | AC49: Aplicar sobre el cabello mojado, masajear el cuero cabelludo con movimientos suaves y enjuagar bien. | AD49: Leite vegetal | Pantenol | AE49: Leche vegetal | Pantenol | AH49: shampoo-doce-de-leite-300ml.webp | AI49: shampoo-doce-de-leite-300ml_02.webp | AJ49: Quienes buscan una rutina de cuidado perfumada para cabello y piel | AK49: https://haskellcosmeticos.com.br/tratamentos-capilares/doce-de-leite-vicosa/ | AL49: 2026-07-24 | AM49: =IF(ISBLANK(Q49),"",Q49*Parametros_PEN!$B$2) | AN49: =IF(ISBLANK(Q49),"",Q49*Parametros_PEN!$B$2*(1+Parametros_PEN!$B$3)) | AO49: =IF(ISBLANK(R49),"",R49*Parametros_PEN!$B$2) | AP49: =IF(ISBLANK(R49),"",R49*Parametros_PEN!$B$2*(1+Parametros_PEN!$B$3))
A50: HSK-0049 | B50: fluido-engrosador-encorpa-cabelo-120-ml | D50: Haskell | E50: Fluido Engrossador Encorpa Cabelo 120ml | F50: Fluido engrosador Encorpa Cabelo 120 ml | G50: Encorpa Cabelo | H50: Tratamentos Capilares | I50: Tratamientos capilares | J50: Volume para cabelo fino | K50: Volumen para cabello fino | L50: Fluido | M50: Fluido finalizador | N50: 120 ml | O50: 120 | P50: ml | Q50: 48.9 | S50: =IF(ISBLANK(R50),0,IFERROR((Q50-R50)/Q50,0)) | T50: =R50<>"" | U50: =TRUE() | W50: Fluido finalizador sin enjuague de la linea Encorpa Cabelo: aumenta el espesor aparente del cabello fino y con poco volumen, sin apelmazar. | Y50: Finalizador sin enjuague | Facilita el peinado | Protege del calor y de agresiones externas | AA50: Finalizador | AC50: Aplicar sobre el cabello limpio y humedo, distribuir en todo el largo y finalizar como se prefiera. | AD50: Acido hialuronico | Physalis | AE50: Acido hialuronico | Physalis | AH50: fluido-engrossador-encorpa-cabelo-haskell-120ml.webp | AJ50: Cabello fino y con poco volumen | AK50: https://haskellcosmeticos.com.br/tratamentos-capilares/linha-encorpa-cabelo-haskell/ | AL50: 2026-07-24 | AM50: =IF(ISBLANK(Q50),"",Q50*Parametros_PEN!$B$2) | AN50: =IF(ISBLANK(Q50),"",Q50*Parametros_PEN!$B$2*(1+Parametros_PEN!$B$3)) | AO50: =IF(ISBLANK(R50),"",R50*Parametros_PEN!$B$2) | AP50: =IF(ISBLANK(R50),"",R50*Parametros_PEN!$B$2*(1+Parametros_PEN!$B$3))
A51: HSK-0050 | B51: champu-engrosador-encorpa-cabelo-300-ml | D51: Haskell | E51: Shampoo Engrossador Encorpa Cabelo 300ml | F51: Champu engrosador Encorpa Cabelo 300 ml | G51: Encorpa Cabelo | H51: Tratamentos Capilares | I51: Tratamientos capilares | J51: Volume para cabelo fino | K51: Volumen para cabello fino | L51: Shampoo | M51: Champu | N51: 300 ml | O51: 300 | P51: ml | Q51: 62.9 | S51: =IF(ISBLANK(R51),0,IFERROR((Q51-R51)/Q51,0)) | T51: =R51<>"" | U51: =TRUE() | W51: Champu de limpieza suave de la linea Encorpa Cabelo, que prepara el cabello para el tratamiento: aumenta el espesor aparente del cabello fino y con poco volumen, sin apelmazar. | Y51: Limpieza suave sin resecar | Prepara el cabello para el resto de la rutina | Respeta el equilibrio del cuero cabelludo | AA51: Limpiador suave | AC51: Aplicar sobre el cabello mojado, masajear el cuero cabelludo con movimientos suaves y enjuagar bien. | AD51: Acido hialuronico | Physalis | AE51: Acido hialuronico | Physalis | AH51: shampoo-engrossador-encorpa-cabelo-300ml.webp | AJ51: Cabello fino y con poco volumen | AK51: https://haskellcosmeticos.com.br/tratamentos-capilares/linha-encorpa-cabelo-haskell/ | AL51: 2026-07-24 | AM51: =IF(ISBLANK(Q51),"",Q51*Parametros_PEN!$B$2) | AN51: =IF(ISBLANK(Q51),"",Q51*Parametros_PEN!$B$2*(1+Parametros_PEN!$B$3)) | AO51: =IF(ISBLANK(R51),"",R51*Parametros_PEN!$B$2) | AP51: =IF(ISBLANK(R51),"",R51*Parametros_PEN!$B$2*(1+Parametros_PEN!$B$3))
A52: HSK-0051 | B52: acondicionador-engrosador-encorpa-cabelo-300-ml | D52: Haskell | E52: Condicionador Engrossador Encorpa Cabelo 300ml | F52: Acondicionador engrosador Encorpa Cabelo 300 ml | G52: Encorpa Cabelo | H52: Tratamentos Capilares | I52: Tratamientos capilares | J52: Volume para cabelo fino | K52: Volumen para cabello fino | L52: Condicionador | M52: Acondicionador | N52: 300 ml | O52: 300 | P52: ml | Q52: 62.9 | S52: =IF(ISBLANK(R52),0,IFERROR((Q52-R52)/Q52,0)) | T52: =R52<>"" | U52: =TRUE() | W52: Acondicionador de la linea Encorpa Cabelo que facilita el desenredado y sella la cuticula: aumenta el espesor aparente del cabello fino y con poco volumen, sin apelmazar. | Y52: Facilita el desenredado | Sella la cuticula | Aporta suavidad y brillo | AA52: Acondicionador | AC52: Aplicar en el largo y las puntas del cabello despues del champu, dejar actuar unos minutos y enjuagar. | AD52: Acido hialuronico | Physalis | AE52: Acido hialuronico | Physalis | AH52: condicionador-engrossador-encorpa-cabelo-300ml.webp | AJ52: Cabello fino y con poco volumen | AK52: https://haskellcosmeticos.com.br/tratamentos-capilares/linha-encorpa-cabelo-haskell/ | AL52: 2026-07-24 | AM52: =IF(ISBLANK(Q52),"",Q52*Parametros_PEN!$B$2) | AN52: =IF(ISBLANK(Q52),"",Q52*Parametros_PEN!$B$2*(1+Parametros_PEN!$B$3)) | AO52: =IF(ISBLANK(R52),"",R52*Parametros_PEN!$B$2) | AP52: =IF(ISBLANK(R52),"",R52*Parametros_PEN!$B$2*(1+Parametros_PEN!$B$3))
A53: HSK-0052 | B53: mascarilla-engrosadora-encorpa-cabelo-300-g | D53: Haskell | E53: Mascara Engrossadora Encorpa Cabelo 300g | F53: Mascarilla engrosadora Encorpa Cabelo 300 g | G53: Encorpa Cabelo | H53: Tratamentos Capilares | I53: Tratamientos capilares | J53: Volume para cabelo fino | K53: Volumen para cabello fino | L53: Mascara de Tratamento | M53: Mascarilla de tratamiento | N53: 300 g | O53: 300 | P53: g | Q53: 74.9 | S53: =IF(ISBLANK(R53),0,IFERROR((Q53-R53)/Q53,0)) | T53: =R53<>"" | U53: =TRUE() | W53: Mascarilla de tratamiento concentrada de la linea Encorpa Cabelo, de uso posterior al champu: aumenta el espesor aparente del cabello fino y con poco volumen, sin apelmazar. | Y53: Tratamiento concentrado | Actua en profundidad sobre la fibra capilar | Refuerza el resultado de la linea | AA53: Tratamiento intensivo | AC53: Aplicar mechon por mechon despues del champu, dejar actuar de 3 a 5 minutos y enjuagar bien. | AD53: Acido hialuronico | Physalis | AE53: Acido hialuronico | Physalis | AH53: mascara-engrossadora-encorpa-cabelo-300g.webp | AJ53: Cabello fino y con poco volumen | AK53: https://haskellcosmeticos.com.br/tratamentos-capilares/linha-encorpa-cabelo-haskell/ | AL53: 2026-07-24 | AM53: =IF(ISBLANK(Q53),"",Q53*Parametros_PEN!$B$2) | AN53: =IF(ISBLANK(Q53),"",Q53*Parametros_PEN!$B$2*(1+Parametros_PEN!$B$3)) | AO53: =IF(ISBLANK(R53),"",R53*Parametros_PEN!$B$2) | AP53: =IF(ISBLANK(R53),"",R53*Parametros_PEN!$B$2*(1+Parametros_PEN!$B$3))
A54: HSK-0053 | B54: pomada-modeladora-encorpa-cabelo-150-g | D54: Haskell | E54: Pomada Modeladora Encorpa Cabelo 150g | F54: Pomada modeladora Encorpa Cabelo 150 g | G54: Encorpa Cabelo | H54: Tratamentos Capilares | I54: Tratamientos capilares | J54: Volume para cabelo fino | K54: Volumen para cabello fino | L54: Pomada | M54: Pomada modeladora | N54: 150 g | O54: 150 | P54: g | Q54: 60.9 | S54: =IF(ISBLANK(R54),0,IFERROR((Q54-R54)/Q54,0)) | T54: =R54<>"" | U54: =TRUE() | W54: Pomada modeladora de la linea Encorpa Cabelo que fija y da forma al peinado: aumenta el espesor aparente del cabello fino y con poco volumen, sin apelmazar. | Y54: Fija el peinado | Da forma y control | Textura maleable | AA54: Modelador | AC54: Tomar una pequena cantidad, calentar entre las manos y aplicar sobre el cabello seco para modelar. | AD54: Acido hialuronico | Physalis | AE54: Acido hialuronico | Physalis | AH54: pomada-modeladora-encorpa-cabelo-150g.webp | AJ54: Cabello fino y con poco volumen | AK54: https://haskellcosmeticos.com.br/tratamentos-capilares/linha-encorpa-cabelo-haskell/ | AL54: 2026-07-24 | AM54: =IF(ISBLANK(Q54),"",Q54*Parametros_PEN!$B$2) | AN54: =IF(ISBLANK(Q54),"",Q54*Parametros_PEN!$B$2*(1+Parametros_PEN!$B$3)) | AO54: =IF(ISBLANK(R54),"",R54*Parametros_PEN!$B$2) | AP54: =IF(ISBLANK(R54),"",R54*Parametros_PEN!$B$2*(1+Parametros_PEN!$B$3))
A55: HSK-0054 | B55: champu-engrosador-encorpa-cabelo-500-ml | D55: Haskell | E55: Shampoo Engrossador Encorpa Cabelo 500ml | F55: Champu engrosador Encorpa Cabelo 500 ml | G55: Encorpa Cabelo | H55: Tratamentos Capilares | I55: Tratamientos capilares | J55: Volume para cabelo fino | K55: Volumen para cabello fino | L55: Shampoo | M55: Champu | N55: 500 ml | O55: 500 | P55: ml | Q55: 84.9 | S55: =IF(ISBLANK(R55),0,IFERROR((Q55-R55)/Q55,0)) | T55: =R55<>"" | U55: =TRUE() | W55: Champu de limpieza suave de la linea Encorpa Cabelo, que prepara el cabello para el tratamiento: aumenta el espesor aparente del cabello fino y con poco volumen, sin apelmazar. | Y55: Limpieza suave sin resecar | Prepara el cabello para el resto de la rutina | Respeta el equilibrio del cuero cabelludo | AA55: Limpiador suave | AC55: Aplicar sobre el cabello mojado, masajear el cuero cabelludo con movimientos suaves y enjuagar bien. | AD55: Acido hialuronico | Physalis | AE55: Acido hialuronico | Physalis | AH55: shampoo-engrossador-encorpa-cabelo-500ml.webp | AJ55: Cabello fino y con poco volumen | AK55: https://haskellcosmeticos.com.br/tratamentos-capilares/linha-encorpa-cabelo-haskell/ | AL55: 2026-07-24 | AM55: =IF(ISBLANK(Q55),"",Q55*Parametros_PEN!$B$2) | AN55: =IF(ISBLANK(Q55),"",Q55*Parametros_PEN!$B$2*(1+Parametros_PEN!$B$3)) | AO55: =IF(ISBLANK(R55),"",R55*Parametros_PEN!$B$2) | AP55: =IF(ISBLANK(R55),"",R55*Parametros_PEN!$B$2*(1+Parametros_PEN!$B$3))
A56: HSK-0055 | B56: acondicionador-engrosador-encorpa-cabelo-500-ml | D56: Haskell | E56: Condicionador Engrossador Encorpa Cabelo 500ml | F56: Acondicionador engrosador Encorpa Cabelo 500 ml | G56: Encorpa Cabelo | H56: Tratamentos Capilares | I56: Tratamientos capilares | J56: Volume para cabelo fino | K56: Volumen para cabello fino | L56: Condicionador | M56: Acondicionador | N56: 500 ml | O56: 500 | P56: ml | Q56: 84.9 | S56: =IF(ISBLANK(R56),0,IFERROR((Q56-R56)/Q56,0)) | T56: =R56<>"" | U56: =TRUE() | W56: Acondicionador de la linea Encorpa Cabelo que facilita el desenredado y sella la cuticula: aumenta el espesor aparente del cabello fino y con poco volumen, sin apelmazar. | Y56: Facilita el desenredado | Sella la cuticula | Aporta suavidad y brillo | AA56: Acondicionador | AC56: Aplicar en el largo y las puntas del cabello despues del champu, dejar actuar unos minutos y enjuagar. | AD56: Acido hialuronico | Physalis | AE56: Acido hialuronico | Physalis | AH56: condicionador-engrossador-encorpa-cabelo-500ml.webp | AJ56: Cabello fino y con poco volumen | AK56: https://haskellcosmeticos.com.br/tratamentos-capilares/linha-encorpa-cabelo-haskell/ | AL56: 2026-07-24 | AM56: =IF(ISBLANK(Q56),"",Q56*Parametros_PEN!$B$2) | AN56: =IF(ISBLANK(Q56),"",Q56*Parametros_PEN!$B$2*(1+Parametros_PEN!$B$3)) | AO56: =IF(ISBLANK(R56),"",R56*Parametros_PEN!$B$2) | AP56: =IF(ISBLANK(R56),"",R56*Parametros_PEN!$B$2*(1+Parametros_PEN!$B$3))
A57: HSK-0056 | B57: champu-anticaspa-pra-eles-250-ml | D57: Haskell | E57: Shampoo Anticaspa Pra Eles 250ml | F57: Champu anticaspa Pra Eles 250 ml | G57: Pra Eles (H) | H57: Tratamentos Capilares | I57: Tratamientos capilares | J57: Linha masculina | K57: Linea masculina | L57: Shampoo | M57: Champu | N57: 250 ml | O57: 250 | P57: ml | Q57: 53.9 | S57: =IF(ISBLANK(R57),0,IFERROR((Q57-R57)/Q57,0)) | T57: =R57<>"" | U57: =TRUE() | W57: Champu de limpieza suave de la linea Pra Eles (H), que prepara el cabello para el tratamiento: cuida el cabello y la barba con una rutina practica pensada para el publico masculino. | Y57: Limpieza suave sin resecar | Prepara el cabello para el resto de la rutina | Respeta el equilibrio del cuero cabelludo | AA57: Limpiador suave | AC57: Aplicar sobre el cabello mojado, masajear el cuero cabelludo con movimientos suaves y enjuagar bien. | AH57: shampoo-anticaspa-pra-eles-250ml.webp | AJ57: Cabello y barba masculinos | AK57: https://haskellcosmeticos.com.br/tratamentos-capilares/linha-h-haskell/ | AL57: 2026-07-24 | AM57: =IF(ISBLANK(Q57),"",Q57*Parametros_PEN!$B$2) | AN57: =IF(ISBLANK(Q57),"",Q57*Parametros_PEN!$B$2*(1+Parametros_PEN!$B$3)) | AO57: =IF(ISBLANK(R57),"",R57*Parametros_PEN!$B$2) | AP57: =IF(ISBLANK(R57),"",R57*Parametros_PEN!$B$2*(1+Parametros_PEN!$B$3))
A58: HSK-0057 | B58: champu-cabello-y-barba-pra-eles-250-ml | D58: Haskell | E58: Shampoo Cabelo & Barba Pra Eles 250ml | F58: Champu cabello y barba Pra Eles 250 ml | G58: Pra Eles (H) | H58: Tratamentos Capilares | I58: Tratamientos capilares | J58: Linha masculina | K58: Linea masculina | L58: Shampoo | M58: Champu | N58: 250 ml | O58: 250 | P58: ml | Q58: 46.9 | S58: =IF(ISBLANK(R58),0,IFERROR((Q58-R58)/Q58,0)) | T58: =R58<>"" | U58: =TRUE() | W58: Champu de limpieza suave de la linea Pra Eles (H), que prepara el cabello para el tratamiento: cuida el cabello y la barba con una rutina practica pensada para el publico masculino. | Y58: Limpieza suave sin resecar | Prepara el cabello para el resto de la rutina | Respeta el equilibrio del cuero cabelludo | AA58: Limpiador suave | AC58: Aplicar sobre el cabello mojado, masajear el cuero cabelludo con movimientos suaves y enjuagar bien. | AH58: shampoo-cabelo-barba-pra-eles-250ml.webp | AJ58: Cabello y barba masculinos | AK58: https://haskellcosmeticos.com.br/tratamentos-capilares/linha-h-haskell/ | AL58: 2026-07-24 | AM58: =IF(ISBLANK(Q58),"",Q58*Parametros_PEN!$B$2) | AN58: =IF(ISBLANK(Q58),"",Q58*Parametros_PEN!$B$2*(1+Parametros_PEN!$B$3)) | AO58: =IF(ISBLANK(R58),"",R58*Parametros_PEN!$B$2) | AP58: =IF(ISBLANK(R58),"",R58*Parametros_PEN!$B$2*(1+Parametros_PEN!$B$3))
A59: HSK-0058 | B59: crema-multifunciones-pra-eles-150-g | D59: Haskell | E59: Creme Multifuncoes Pra Eles 150g | F59: Crema multifunciones Pra Eles 150 g | G59: Pra Eles (H) | H59: Tratamentos Capilares | I59: Tratamientos capilares | J59: Linha masculina | K59: Linea masculina | L59: Creme | M59: Crema | N59: 150 g | O59: 150 | P59: g | Q59: 52.9 | S59: =IF(ISBLANK(R59),0,IFERROR((Q59-R59)/Q59,0)) | T59: =R59<>"" | U59: =TRUE() | W59: Crema de la linea Pra Eles (H): cuida el cabello y la barba con una rutina practica pensada para el publico masculino. | Y59: Facilita el peinado | Hidrata y da forma segun el uso | AA59: Multifuncion | AC59: Aplicar sobre el cabello humedo o seco, segun la necesidad, y finalizar como se prefiera. | AH59: creme-multifuncoes-pra-eles-150g.webp | AJ59: Cabello y barba masculinos | AK59: https://haskellcosmeticos.com.br/tratamentos-capilares/linha-h-haskell/ | AL59: 2026-07-24 | AM59: =IF(ISBLANK(Q59),"",Q59*Parametros_PEN!$B$2) | AN59: =IF(ISBLANK(Q59),"",Q59*Parametros_PEN!$B$2*(1+Parametros_PEN!$B$3)) | AO59: =IF(ISBLANK(R59),"",R59*Parametros_PEN!$B$2) | AP59: =IF(ISBLANK(R59),"",R59*Parametros_PEN!$B$2*(1+Parametros_PEN!$B$3))
A60: HSK-0059 | B60: pomada-modeladora-pra-eles-55-g | D60: Haskell | E60: Pomada Modeladora Pra Eles 55g | F60: Pomada modeladora Pra Eles 55 g | G60: Pra Eles (H) | H60: Tratamentos Capilares | I60: Tratamientos capilares | J60: Linha masculina | K60: Linea masculina | L60: Pomada | M60: Pomada modeladora | N60: 55 g | O60: 55 | P60: g | Q60: 68.9 | S60: =IF(ISBLANK(R60),0,IFERROR((Q60-R60)/Q60,0)) | T60: =R60<>"" | U60: =TRUE() | W60: Pomada modeladora de la linea Pra Eles (H) que fija y da forma al peinado: cuida el cabello y la barba con una rutina practica pensada para el publico masculino. | Y60: Fija el peinado | Da forma y control | Textura maleable | AA60: Modelador | AC60: Tomar una pequena cantidad, calentar entre las manos y aplicar sobre el cabello seco para modelar. | AH60: pomada-modeladora-pra-eles-55g.webp | AJ60: Cabello y barba masculinos | AK60: https://haskellcosmeticos.com.br/tratamentos-capilares/linha-h-haskell/ | AL60: 2026-07-24 | AM60: =IF(ISBLANK(Q60),"",Q60*Parametros_PEN!$B$2) | AN60: =IF(ISBLANK(Q60),"",Q60*Parametros_PEN!$B$2*(1+Parametros_PEN!$B$3)) | AO60: =IF(ISBLANK(R60),"",R60*Parametros_PEN!$B$2) | AP60: =IF(ISBLANK(R60),"",R60*Parametros_PEN!$B$2*(1+Parametros_PEN!$B$3))
A61: HSK-0060 | B61: champu-hidranutre-300-ml | D61: Haskell | E61: Shampoo Hidranutre 300ml | F61: Champu Hidranutre 300 ml | G61: Hidranutre | H61: Tratamentos Capilares | I61: Tratamientos capilares | J61: Hidratacao e nutricao combinadas | K61: Hidratacion y nutricion combinadas | L61: Shampoo | M61: Champu | N61: 300 ml | O61: 300 | P61: ml | Q61: 62.9 | S61: =IF(ISBLANK(R61),0,IFERROR((Q61-R61)/Q61,0)) | T61: =R61<>"" | U61: =TRUE() | W61: Champu de limpieza suave de la linea Hidranutre, que prepara el cabello para el tratamiento: combina hidratacion y nutricion en una sola rutina, ideal para quien busca practicidad. | Y61: Limpieza suave sin resecar | Prepara el cabello para el resto de la rutina | Respeta el equilibrio del cuero cabelludo | AA61: Limpiador suave | AC61: Aplicar sobre el cabello mojado, masajear el cuero cabelludo con movimientos suaves y enjuagar bien. | AD61: Cana-de-acucar | Oleo de ricino | AE61: Cana de azucar | Aceite de ricino | AH61: shampoo-hidranutre-300ml.webp | AJ61: Todo tipo de cabello | AK61: https://haskellcosmeticos.com.br/tratamentos-capilares/hidranutre/ | AL61: 2026-07-24 | AM61: =IF(ISBLANK(Q61),"",Q61*Parametros_PEN!$B$2) | AN61: =IF(ISBLANK(Q61),"",Q61*Parametros_PEN!$B$2*(1+Parametros_PEN!$B$3)) | AO61: =IF(ISBLANK(R61),"",R61*Parametros_PEN!$B$2) | AP61: =IF(ISBLANK(R61),"",R61*Parametros_PEN!$B$2*(1+Parametros_PEN!$B$3))
A62: HSK-0061 | B62: champu-hidranutre-500-ml | D62: Haskell | E62: Shampoo Hidranutre 500ml | F62: Champu Hidranutre 500 ml | G62: Hidranutre | H62: Tratamentos Capilares | I62: Tratamientos capilares | J62: Hidratacao e nutricao combinadas | K62: Hidratacion y nutricion combinadas | L62: Shampoo | M62: Champu | N62: 500 ml | O62: 500 | P62: ml | Q62: 84.9 | S62: =IF(ISBLANK(R62),0,IFERROR((Q62-R62)/Q62,0)) | T62: =R62<>"" | U62: =TRUE() | W62: Champu de limpieza suave de la linea Hidranutre, que prepara el cabello para el tratamiento: combina hidratacion y nutricion en una sola rutina, ideal para quien busca practicidad. | Y62: Limpieza suave sin resecar | Prepara el cabello para el resto de la rutina | Respeta el equilibrio del cuero cabelludo | AA62: Limpiador suave | AC62: Aplicar sobre el cabello mojado, masajear el cuero cabelludo con movimientos suaves y enjuagar bien. | AD62: Cana-de-acucar | Oleo de ricino | AE62: Cana de azucar | Aceite de ricino | AH62: shampoo-hidranutre-500ml.webp | AJ62: Todo tipo de cabello | AK62: https://haskellcosmeticos.com.br/tratamentos-capilares/hidranutre/ | AL62: 2026-07-24 | AM62: =IF(ISBLANK(Q62),"",Q62*Parametros_PEN!$B$2) | AN62: =IF(ISBLANK(Q62),"",Q62*Parametros_PEN!$B$2*(1+Parametros_PEN!$B$3)) | AO62: =IF(ISBLANK(R62),"",R62*Parametros_PEN!$B$2) | AP62: =IF(ISBLANK(R62),"",R62*Parametros_PEN!$B$2*(1+Parametros_PEN!$B$3))
A63: HSK-0062 | B63: acondicionador-hidranutre-300-ml | D63: Haskell | E63: Condicionador Hidranutre 300ml | F63: Acondicionador Hidranutre 300 ml | G63: Hidranutre | H63: Tratamentos Capilares | I63: Tratamientos capilares | J63: Hidratacao e nutricao combinadas | K63: Hidratacion y nutricion combinadas | L63: Condicionador | M63: Acondicionador | N63: 300 ml | O63: 300 | P63: ml | Q63: 62.9 | S63: =IF(ISBLANK(R63),0,IFERROR((Q63-R63)/Q63,0)) | T63: =R63<>"" | U63: =TRUE() | W63: Acondicionador de la linea Hidranutre que facilita el desenredado y sella la cuticula: combina hidratacion y nutricion en una sola rutina, ideal para quien busca practicidad. | Y63: Facilita el desenredado | Sella la cuticula | Aporta suavidad y brillo | AA63: Acondicionador | AC63: Aplicar en el largo y las puntas del cabello despues del champu, dejar actuar unos minutos y enjuagar. | AD63: Cana-de-acucar | Oleo de ricino | AE63: Cana de azucar | Aceite de ricino | AH63: condicionador-hidranutre-300ml.webp | AJ63: Todo tipo de cabello | AK63: https://haskellcosmeticos.com.br/tratamentos-capilares/hidranutre/ | AL63: 2026-07-24 | AM63: =IF(ISBLANK(Q63),"",Q63*Parametros_PEN!$B$2) | AN63: =IF(ISBLANK(Q63),"",Q63*Parametros_PEN!$B$2*(1+Parametros_PEN!$B$3)) | AO63: =IF(ISBLANK(R63),"",R63*Parametros_PEN!$B$2) | AP63: =IF(ISBLANK(R63),"",R63*Parametros_PEN!$B$2*(1+Parametros_PEN!$B$3))
A64: HSK-0063 | B64: acondicionador-hidranutre-500-ml | D64: Haskell | E64: Condicionador Hidranutre 500ml | F64: Acondicionador Hidranutre 500 ml | G64: Hidranutre | H64: Tratamentos Capilares | I64: Tratamientos capilares | J64: Hidratacao e nutricao combinadas | K64: Hidratacion y nutricion combinadas | L64: Condicionador | M64: Acondicionador | N64: 500 ml | O64: 500 | P64: ml | Q64: 84.9 | S64: =IF(ISBLANK(R64),0,IFERROR((Q64-R64)/Q64,0)) | T64: =R64<>"" | U64: =TRUE() | W64: Acondicionador de la linea Hidranutre que facilita el desenredado y sella la cuticula: combina hidratacion y nutricion en una sola rutina, ideal para quien busca practicidad. | Y64: Facilita el desenredado | Sella la cuticula | Aporta suavidad y brillo | AA64: Acondicionador | AC64: Aplicar en el largo y las puntas del cabello despues del champu, dejar actuar unos minutos y enjuagar. | AD64: Cana-de-acucar | Oleo de ricino | AE64: Cana de azucar | Aceite de ricino | AH64: condicionador-hidranutre-haskell-500ml.webp | AJ64: Todo tipo de cabello | AK64: https://haskellcosmeticos.com.br/tratamentos-capilares/hidranutre/ | AL64: 2026-07-24 | AM64: =IF(ISBLANK(Q64),"",Q64*Parametros_PEN!$B$2) | AN64: =IF(ISBLANK(Q64),"",Q64*Parametros_PEN!$B$2*(1+Parametros_PEN!$B$3)) | AO64: =IF(ISBLANK(R64),"",R64*Parametros_PEN!$B$2) | AP64: =IF(ISBLANK(R64),"",R64*Parametros_PEN!$B$2*(1+Parametros_PEN!$B$3))
A65: HSK-0064 | B65: mascarilla-de-tratamiento-hidranutre-300-g | D65: Haskell | E65: Mascara de Tratamento Hidranutre 300g | F65: Mascarilla de tratamiento Hidranutre 300 g | G65: Hidranutre | H65: Tratamentos Capilares | I65: Tratamientos capilares | J65: Hidratacao e nutricao combinadas | K65: Hidratacion y nutricion combinadas | L65: Mascara de Tratamento | M65: Mascarilla de tratamiento | N65: 300 g | O65: 300 | P65: g | Q65: 74.9 | S65: =IF(ISBLANK(R65),0,IFERROR((Q65-R65)/Q65,0)) | T65: =R65<>"" | U65: =TRUE() | W65: Mascarilla de tratamiento concentrada de la linea Hidranutre, de uso posterior al champu: combina hidratacion y nutricion en una sola rutina, ideal para quien busca practicidad. | Y65: Tratamiento concentrado | Actua en profundidad sobre la fibra capilar | Refuerza el resultado de la linea | AA65: Tratamiento intensivo | AC65: Aplicar mechon por mechon despues del champu, dejar actuar de 3 a 5 minutos y enjuagar bien. | AD65: Cana-de-acucar | Oleo de ricino | AE65: Cana de azucar | Aceite de ricino | AH65: mascara-de-tratamento-hidranutre-300g.webp | AJ65: Todo tipo de cabello | AK65: https://haskellcosmeticos.com.br/tratamentos-capilares/hidranutre/ | AL65: 2026-07-24 | AM65: =IF(ISBLANK(Q65),"",Q65*Parametros_PEN!$B$2) | AN65: =IF(ISBLANK(Q65),"",Q65*Parametros_PEN!$B$2*(1+Parametros_PEN!$B$3)) | AO65: =IF(ISBLANK(R65),"",R65*Parametros_PEN!$B$2) | AP65: =IF(ISBLANK(R65),"",R65*Parametros_PEN!$B$2*(1+Parametros_PEN!$B$3))
A66: HSK-0065 | B66: mascarilla-de-tratamiento-hidranutre-500-g | D66: Haskell | E66: Mascara de Tratamento Hidranutre 500g | F66: Mascarilla de tratamiento Hidranutre 500 g | G66: Hidranutre | H66: Tratamentos Capilares | I66: Tratamientos capilares | J66: Hidratacao e nutricao combinadas | K66: Hidratacion y nutricion combinadas | L66: Mascara de Tratamento | M66: Mascarilla de tratamiento | N66: 500 g | O66: 500 | P66: g | Q66: 89.9 | S66: =IF(ISBLANK(R66),0,IFERROR((Q66-R66)/Q66,0)) | T66: =R66<>"" | U66: =TRUE() | W66: Mascarilla de tratamiento concentrada de la linea Hidranutre, de uso posterior al champu: combina hidratacion y nutricion en una sola rutina, ideal para quien busca practicidad. | Y66: Tratamiento concentrado | Actua en profundidad sobre la fibra capilar | Refuerza el resultado de la linea | AA66: Tratamiento intensivo | AC66: Aplicar mechon por mechon despues del champu, dejar actuar de 3 a 5 minutos y enjuagar bien. | AD66: Cana-de-acucar | Oleo de ricino | AE66: Cana de azucar | Aceite de ricino | AH66: mascara-de-tratamento-hidranutre-500g.webp | AJ66: Todo tipo de cabello | AK66: https://haskellcosmeticos.com.br/tratamentos-capilares/hidranutre/ | AL66: 2026-07-24 | AM66: =IF(ISBLANK(Q66),"",Q66*Parametros_PEN!$B$2) | AN66: =IF(ISBLANK(Q66),"",Q66*Parametros_PEN!$B$2*(1+Parametros_PEN!$B$3)) | AO66: =IF(ISBLANK(R66),"",R66*Parametros_PEN!$B$2) | AP66: =IF(ISBLANK(R66),"",R66*Parametros_PEN!$B$2*(1+Parametros_PEN!$B$3))
A67: HSK-0066 | B67: leave-in-hidranutre-150-g | D67: Haskell | E67: Leave In Hidranutre 150g | F67: Leave-in Hidranutre 150 g | G67: Hidranutre | H67: Tratamentos Capilares | I67: Tratamientos capilares | J67: Hidratacao e nutricao combinadas | K67: Hidratacion y nutricion combinadas | L67: Leave In | M67: Leave-in | N67: 150 g | O67: 150 | P67: g | Q67: 59.9 | S67: =IF(ISBLANK(R67),0,IFERROR((Q67-R67)/Q67,0)) | T67: =R67<>"" | U67: =TRUE() | W67: Leave-in sin enjuague de la linea Hidranutre que facilita el peinado: combina hidratacion y nutricion en una sola rutina, ideal para quien busca practicidad. | Y67: Facilita el peinado | Reduce el frizz | Protege del calor | AA67: Leave-in | AC67: Aplicar sobre el cabello limpio y humedo, sin enjuagar, y finalizar como se prefiera. | AD67: Cana-de-acucar | Oleo de ricino | AE67: Cana de azucar | Aceite de ricino | AH67: leave-in-hidranutre-150g.webp | AJ67: Todo tipo de cabello | AK67: https://haskellcosmeticos.com.br/tratamentos-capilares/hidranutre/ | AL67: 2026-07-24 | AM67: =IF(ISBLANK(Q67),"",Q67*Parametros_PEN!$B$2) | AN67: =IF(ISBLANK(Q67),"",Q67*Parametros_PEN!$B$2*(1+Parametros_PEN!$B$3)) | AO67: =IF(ISBLANK(R67),"",R67*Parametros_PEN!$B$2) | AP67: =IF(ISBLANK(R67),"",R67*Parametros_PEN!$B$2*(1+Parametros_PEN!$B$3))
A68: HSK-0067 | B68: serum-hidranutre-35-ml | D68: Haskell | E68: Serum Hidranutre 35ml | F68: Serum Hidranutre 35 ml | G68: Hidranutre | H68: Tratamentos Capilares | I68: Tratamientos capilares | J68: Hidratacao e nutricao combinadas | K68: Hidratacion y nutricion combinadas | L68: Serum | M68: Serum capilar | N68: 35 ml | O68: 35 | P68: ml | Q68: 61.9 | S68: =IF(ISBLANK(R68),0,IFERROR((Q68-R68)/Q68,0)) | T68: =R68<>"" | U68: =TRUE() | W68: Serum capilar sin enjuague de la linea Hidranutre, de textura liviana: combina hidratacion y nutricion en una sola rutina, ideal para quien busca practicidad. | Y68: Aporta brillo intenso | Ayuda a controlar el frizz | Textura liviana, no apelmaza | AA68: Serum finalizador | AC68: Aplicar una pequena cantidad en el largo y las puntas del cabello seco o humedo. | AD68: Cana-de-acucar | Oleo de ricino | AE68: Cana de azucar | Aceite de ricino | AH68: serum-hidranutre-35ml.webp | AJ68: Todo tipo de cabello | AK68: https://haskellcosmeticos.com.br/tratamentos-capilares/hidranutre/ | AL68: 2026-07-24 | AM68: =IF(ISBLANK(Q68),"",Q68*Parametros_PEN!$B$2) | AN68: =IF(ISBLANK(Q68),"",Q68*Parametros_PEN!$B$2*(1+Parametros_PEN!$B$3)) | AO68: =IF(ISBLANK(R68),"",R68*Parametros_PEN!$B$2) | AP68: =IF(ISBLANK(R68),"",R68*Parametros_PEN!$B$2*(1+Parametros_PEN!$B$3))
A69: HSK-0068 | B69: aceite-nutritivo-infusion-de-aceites-100-ml | D69: Haskell | E69: Oleo Nutritivo Infusao de Oleos 100ml | F69: Aceite nutritivo Infusion de Aceites 100 ml | G69: Infusao de Oleos | H69: Tratamentos Capilares | I69: Tratamientos capilares | J69: Nutricao ultraprofunda | K69: Nutricion ultraprofunda | L69: Oleo | M69: Aceite capilar | N69: 100 ml | O69: 100 | P69: ml | Q69: 95.9 | S69: =IF(ISBLANK(R69),0,IFERROR((Q69-R69)/Q69,0)) | T69: =R69<>"" | U69: =TRUE() | W69: Aceite capilar finalizador de la linea Infusao de Oleos, que aporta brillo: ofrece nutricion ultraprofunda para cabello muy reseco y opaco. | Y69: Aporta brillo | Sella las puntas | Protege del resecamiento | AA69: Aceite finalizador | AC69: Aplicar unas gotas en el largo y las puntas del cabello seco o humedo. | AD69: Oleo de marula | Oleo de argan | Oleo de monoi | AE69: Aceite de marula | Aceite de argan | Aceite de monoi | AH69: oleo-nutritivo-infusao-de-oleos-100ml.webp | AI69: oleo-nutritivo-infusao-de-oleos-100ml_02.webp | oleo-nutritivo-infusao-de-oleos-100ml_03.webp | AJ69: Cabello muy reseco y opaco | AK69: https://haskellcosmeticos.com.br/tratamentos-capilares/infusao-de-oleos/ | AL69: 2026-07-24 | AM69: =IF(ISBLANK(Q69),"",Q69*Parametros_PEN!$B$2) | AN69: =IF(ISBLANK(Q69),"",Q69*Parametros_PEN!$B$2*(1+Parametros_PEN!$B$3)) | AO69: =IF(ISBLANK(R69),"",R69*Parametros_PEN!$B$2) | AP69: =IF(ISBLANK(R69),"",R69*Parametros_PEN!$B$2*(1+Parametros_PEN!$B$3))
A70: HSK-0069 | B70: mascarilla-de-tratamiento-infusion-de-aceites-500-g | D70: Haskell | E70: Mascara de Tratamento Infusao de Oleos 500g | F70: Mascarilla de tratamiento Infusion de Aceites 500 g | G70: Infusao de Oleos | H70: Tratamentos Capilares | I70: Tratamientos capilares | J70: Nutricao ultraprofunda | K70: Nutricion ultraprofunda | L70: Mascara de Tratamento | M70: Mascarilla de tratamiento | N70: 500 g | O70: 500 | P70: g | Q70: 89.9 | S70: =IF(ISBLANK(R70),0,IFERROR((Q70-R70)/Q70,0)) | T70: =R70<>"" | U70: =TRUE() | W70: Mascarilla de tratamiento concentrada de la linea Infusao de Oleos, de uso posterior al champu: ofrece nutricion ultraprofunda para cabello muy reseco y opaco. | Y70: Tratamiento concentrado | Actua en profundidad sobre la fibra capilar | Refuerza el resultado de la linea | AA70: Tratamiento intensivo | AC70: Aplicar mechon por mechon despues del champu, dejar actuar de 3 a 5 minutos y enjuagar bien. | AD70: Oleo de marula | Oleo de argan | Oleo de monoi | AE70: Aceite de marula | Aceite de argan | Aceite de monoi | AH70: mascara-de-tratamento-infusao-de-oleos-500g.webp | AJ70: Cabello muy reseco y opaco | AK70: https://haskellcosmeticos.com.br/tratamentos-capilares/infusao-de-oleos/ | AL70: 2026-07-24 | AM70: =IF(ISBLANK(Q70),"",Q70*Parametros_PEN!$B$2) | AN70: =IF(ISBLANK(Q70),"",Q70*Parametros_PEN!$B$2*(1+Parametros_PEN!$B$3)) | AO70: =IF(ISBLANK(R70),"",R70*Parametros_PEN!$B$2) | AP70: =IF(ISBLANK(R70),"",R70*Parametros_PEN!$B$2*(1+Parametros_PEN!$B$3))
A71: HSK-0070 | B71: acondicionador-infusion-de-aceites-500-ml | D71: Haskell | E71: Condicionador Infusao de Oleos 500ml | F71: Acondicionador Infusion de Aceites 500 ml | G71: Infusao de Oleos | H71: Tratamentos Capilares | I71: Tratamientos capilares | J71: Nutricao ultraprofunda | K71: Nutricion ultraprofunda | L71: Condicionador | M71: Acondicionador | N71: 500 ml | O71: 500 | P71: ml | Q71: 84.9 | S71: =IF(ISBLANK(R71),0,IFERROR((Q71-R71)/Q71,0)) | T71: =R71<>"" | U71: =TRUE() | W71: Acondicionador de la linea Infusao de Oleos que facilita el desenredado y sella la cuticula: ofrece nutricion ultraprofunda para cabello muy reseco y opaco. | Y71: Facilita el desenredado | Sella la cuticula | Aporta suavidad y brillo | AA71: Acondicionador | AC71: Aplicar en el largo y las puntas del cabello despues del champu, dejar actuar unos minutos y enjuagar. | AD71: Oleo de marula | Oleo de argan | Oleo de monoi | AE71: Aceite de marula | Aceite de argan | Aceite de monoi | AH71: condicionador-infusao-de-oleos-500ml.webp | AJ71: Cabello muy reseco y opaco | AK71: https://haskellcosmeticos.com.br/tratamentos-capilares/infusao-de-oleos/ | AL71: 2026-07-24 | AM71: =IF(ISBLANK(Q71),"",Q71*Parametros_PEN!$B$2) | AN71: =IF(ISBLANK(Q71),"",Q71*Parametros_PEN!$B$2*(1+Parametros_PEN!$B$3)) | AO71: =IF(ISBLANK(R71),"",R71*Parametros_PEN!$B$2) | AP71: =IF(ISBLANK(R71),"",R71*Parametros_PEN!$B$2*(1+Parametros_PEN!$B$3))
A72: HSK-0071 | B72: champu-infusion-de-aceites-500-ml | D72: Haskell | E72: Shampoo Infusao de Oleos 500ml | F72: Champu Infusion de Aceites 500 ml | G72: Infusao de Oleos | H72: Tratamentos Capilares | I72: Tratamientos capilares | J72: Nutricao ultraprofunda | K72: Nutricion ultraprofunda | L72: Shampoo | M72: Champu | N72: 500 ml | O72: 500 | P72: ml | Q72: 84.9 | S72: =IF(ISBLANK(R72),0,IFERROR((Q72-R72)/Q72,0)) | T72: =R72<>"" | U72: =TRUE() | W72: Champu de limpieza suave de la linea Infusao de Oleos, que prepara el cabello para el tratamiento: ofrece nutricion ultraprofunda para cabello muy reseco y opaco. | Y72: Limpieza suave sin resecar | Prepara el cabello para el resto de la rutina | Respeta el equilibrio del cuero cabelludo | AA72: Limpiador suave | AC72: Aplicar sobre el cabello mojado, masajear el cuero cabelludo con movimientos suaves y enjuagar bien. | AD72: Oleo de marula | Oleo de argan | Oleo de monoi | AE72: Aceite de marula | Aceite de argan | Aceite de monoi | AH72: shampoo-infusao-de-oleos-500ml.webp | AJ72: Cabello muy reseco y opaco | AK72: https://haskellcosmeticos.com.br/tratamentos-capilares/infusao-de-oleos/ | AL72: 2026-07-24 | AM72: =IF(ISBLANK(Q72),"",Q72*Parametros_PEN!$B$2) | AN72: =IF(ISBLANK(Q72),"",Q72*Parametros_PEN!$B$2*(1+Parametros_PEN!$B$3)) | AO72: =IF(ISBLANK(R72),"",R72*Parametros_PEN!$B$2) | AP72: =IF(ISBLANK(R72),"",R72*Parametros_PEN!$B$2*(1+Parametros_PEN!$B$3))
A73: HSK-0072 | B73: mascarilla-de-tratamiento-infusion-de-aceites-300-g | D73: Haskell | E73: Mascara de Tratamento Infusao de Oleos 300g | F73: Mascarilla de tratamiento Infusion de Aceites 300 g | G73: Infusao de Oleos | H73: Tratamentos Capilares | I73: Tratamientos capilares | J73: Nutricao ultraprofunda | K73: Nutricion ultraprofunda | L73: Mascara de Tratamento | M73: Mascarilla de tratamiento | N73: 300 g | O73: 300 | P73: g | Q73: 74.9 | S73: =IF(ISBLANK(R73),0,IFERROR((Q73-R73)/Q73,0)) | T73: =R73<>"" | U73: =TRUE() | W73: Mascarilla de tratamiento concentrada de la linea Infusao de Oleos, de uso posterior al champu: ofrece nutricion ultraprofunda para cabello muy reseco y opaco. | Y73: Tratamiento concentrado | Actua en profundidad sobre la fibra capilar | Refuerza el resultado de la linea | AA73: Tratamiento intensivo | AC73: Aplicar mechon por mechon despues del champu, dejar actuar de 3 a 5 minutos y enjuagar bien. | AD73: Oleo de marula | Oleo de argan | Oleo de monoi | AE73: Aceite de marula | Aceite de argan | Aceite de monoi | AH73: mascara-de-tratamento-infusao-de-oleos-300g.webp | AJ73: Cabello muy reseco y opaco | AK73: https://haskellcosmeticos.com.br/tratamentos-capilares/infusao-de-oleos/ | AL73: 2026-07-24 | AM73: =IF(ISBLANK(Q73),"",Q73*Parametros_PEN!$B$2) | AN73: =IF(ISBLANK(Q73),"",Q73*Parametros_PEN!$B$2*(1+Parametros_PEN!$B$3)) | AO73: =IF(ISBLANK(R73),"",R73*Parametros_PEN!$B$2) | AP73: =IF(ISBLANK(R73),"",R73*Parametros_PEN!$B$2*(1+Parametros_PEN!$B$3))
A74: HSK-0073 | B74: acondicionador-infusion-de-aceites-300-ml | D74: Haskell | E74: Condicionador Infusao de Oleos 300ml | F74: Acondicionador Infusion de Aceites 300 ml | G74: Infusao de Oleos | H74: Tratamentos Capilares | I74: Tratamientos capilares | J74: Nutricao ultraprofunda | K74: Nutricion ultraprofunda | L74: Condicionador | M74: Acondicionador | N74: 300 ml | O74: 300 | P74: ml | Q74: 62.9 | S74: =IF(ISBLANK(R74),0,IFERROR((Q74-R74)/Q74,0)) | T74: =R74<>"" | U74: =TRUE() | W74: Acondicionador de la linea Infusao de Oleos que facilita el desenredado y sella la cuticula: ofrece nutricion ultraprofunda para cabello muy reseco y opaco. | Y74: Facilita el desenredado | Sella la cuticula | Aporta suavidad y brillo | AA74: Acondicionador | AC74: Aplicar en el largo y las puntas del cabello despues del champu, dejar actuar unos minutos y enjuagar. | AD74: Oleo de marula | Oleo de argan | Oleo de monoi | AE74: Aceite de marula | Aceite de argan | Aceite de monoi | AH74: condicionador-infusao-de-oleos-300ml.webp | AJ74: Cabello muy reseco y opaco | AK74: https://haskellcosmeticos.com.br/tratamentos-capilares/infusao-de-oleos/ | AL74: 2026-07-24 | AM74: =IF(ISBLANK(Q74),"",Q74*Parametros_PEN!$B$2) | AN74: =IF(ISBLANK(Q74),"",Q74*Parametros_PEN!$B$2*(1+Parametros_PEN!$B$3)) | AO74: =IF(ISBLANK(R74),"",R74*Parametros_PEN!$B$2) | AP74: =IF(ISBLANK(R74),"",R74*Parametros_PEN!$B$2*(1+Parametros_PEN!$B$3))
A75: HSK-0074 | B75: champu-jaborandi-anticaida-300-ml | D75: Haskell | E75: Shampoo Jaborandi Antiqueda 300ml | F75: Champu Jaborandi Anticaida 300 ml | G75: Jaborandi Antiqueda | H75: Tratamentos Capilares | I75: Tratamientos capilares | J75: Anti-queda | K75: Anticaida | L75: Shampoo | M75: Champu | N75: 300 ml | O75: 300 | P75: ml | Q75: 58.9 | S75: =IF(ISBLANK(R75),0,IFERROR((Q75-R75)/Q75,0)) | T75: =R75<>"" | U75: =TRUE() | W75: Champu de limpieza suave de la linea Jaborandi Antiqueda, que prepara el cabello para el tratamiento: ayuda a reducir la caida y estimula el crecimiento saludable desde la raiz. | Y75: Limpieza suave sin resecar | Prepara el cabello para el resto de la rutina | Respeta el equilibrio del cuero cabelludo | AA75: Limpiador suave | AC75: Aplicar sobre el cabello mojado, masajear el cuero cabelludo con movimientos suaves y enjuagar bien. | AD75: Extrato de jaborandi | Extrato de nogueira | Extrato de arruda | AE75: Extracto de jaborandi | Extracto de nogal | Extracto de ruda | AH75: shampoo-jaborandi-antiqueda-300ml.webp | AJ75: Cabello con caida, cabello graso o debilitado | AK75: https://haskellcosmeticos.com.br/tratamentos-capilares/linha-jaborandi-haskell/ | AL75: 2026-07-24 | AM75: =IF(ISBLANK(Q75),"",Q75*Parametros_PEN!$B$2) | AN75: =IF(ISBLANK(Q75),"",Q75*Parametros_PEN!$B$2*(1+Parametros_PEN!$B$3)) | AO75: =IF(ISBLANK(R75),"",R75*Parametros_PEN!$B$2) | AP75: =IF(ISBLANK(R75),"",R75*Parametros_PEN!$B$2*(1+Parametros_PEN!$B$3))
A76: HSK-0075 | B76: champu-jaborandi-anticaida-500-ml | D76: Haskell | E76: Shampoo Jaborandi Antiqueda 500ml | F76: Champu Jaborandi Anticaida 500 ml | G76: Jaborandi Antiqueda | H76: Tratamentos Capilares | I76: Tratamientos capilares | J76: Anti-queda | K76: Anticaida | L76: Shampoo | M76: Champu | N76: 500 ml | O76: 500 | P76: ml | Q76: 76.9 | S76: =IF(ISBLANK(R76),0,IFERROR((Q76-R76)/Q76,0)) | T76: =R76<>"" | U76: =TRUE() | W76: Champu de limpieza suave de la linea Jaborandi Antiqueda, que prepara el cabello para el tratamiento: ayuda a reducir la caida y estimula el crecimiento saludable desde la raiz. | Y76: Limpieza suave sin resecar | Prepara el cabello para el resto de la rutina | Respeta el equilibrio del cuero cabelludo | AA76: Limpiador suave | AC76: Aplicar sobre el cabello mojado, masajear el cuero cabelludo con movimientos suaves y enjuagar bien. | AD76: Extrato de jaborandi | Extrato de nogueira | Extrato de arruda | AE76: Extracto de jaborandi | Extracto de nogal | Extracto de ruda | AH76: shampoo-jaborandi-antiqueda-500ml.webp | AJ76: Cabello con caida, cabello graso o debilitado | AK76: https://haskellcosmeticos.com.br/tratamentos-capilares/linha-jaborandi-haskell/ | AL76: 2026-07-24 | AM76: =IF(ISBLANK(Q76),"",Q76*Parametros_PEN!$B$2) | AN76: =IF(ISBLANK(Q76),"",Q76*Parametros_PEN!$B$2*(1+Parametros_PEN!$B$3)) | AO76: =IF(ISBLANK(R76),"",R76*Parametros_PEN!$B$2) | AP76: =IF(ISBLANK(R76),"",R76*Parametros_PEN!$B$2*(1+Parametros_PEN!$B$3))
A77: HSK-0076 | B77: champu-jaborandi-anticaida-1-l | D77: Haskell | E77: Shampoo Jaborandi Antiqueda 1L | F77: Champu Jaborandi Anticaida 1 L | G77: Jaborandi Antiqueda | H77: Tratamentos Capilares | I77: Tratamientos capilares | J77: Anti-queda | K77: Anticaida | L77: Shampoo | M77: Champu | N77: 1000 ml | O77: 1000 | P77: ml | Q77: 118.9 | S77: =IF(ISBLANK(R77),0,IFERROR((Q77-R77)/Q77,0)) | T77: =R77<>"" | U77: =TRUE() | W77: Champu de limpieza suave de la linea Jaborandi Antiqueda, que prepara el cabello para el tratamiento: ayuda a reducir la caida y estimula el crecimiento saludable desde la raiz. | Y77: Limpieza suave sin resecar | Prepara el cabello para el resto de la rutina | Respeta el equilibrio del cuero cabelludo | AA77: Limpiador suave | AC77: Aplicar sobre el cabello mojado, masajear el cuero cabelludo con movimientos suaves y enjuagar bien. | AD77: Extrato de jaborandi | Extrato de nogueira | Extrato de arruda | AE77: Extracto de jaborandi | Extracto de nogal | Extracto de ruda | AH77: shampoo-jaborandi-antiqueda-1l.webp | AJ77: Cabello con caida, cabello graso o debilitado | AK77: https://haskellcosmeticos.com.br/tratamentos-capilares/linha-jaborandi-haskell/ | AL77: 2026-07-24 | AM77: =IF(ISBLANK(Q77),"",Q77*Parametros_PEN!$B$2) | AN77: =IF(ISBLANK(Q77),"",Q77*Parametros_PEN!$B$2*(1+Parametros_PEN!$B$3)) | AO77: =IF(ISBLANK(R77),"",R77*Parametros_PEN!$B$2) | AP77: =IF(ISBLANK(R77),"",R77*Parametros_PEN!$B$2*(1+Parametros_PEN!$B$3))
A78: HSK-0077 | B78: acondicionador-jaborandi-anticaida-300-ml | D78: Haskell | E78: Condicionador Jaborandi Antiqueda 300ml | F78: Acondicionador Jaborandi Anticaida 300 ml | G78: Jaborandi Antiqueda | H78: Tratamentos Capilares | I78: Tratamientos capilares | J78: Anti-queda | K78: Anticaida | L78: Condicionador | M78: Acondicionador | N78: 300 ml | O78: 300 | P78: ml | Q78: 58.9 | S78: =IF(ISBLANK(R78),0,IFERROR((Q78-R78)/Q78,0)) | T78: =R78<>"" | U78: =TRUE() | W78: Acondicionador de la linea Jaborandi Antiqueda que facilita el desenredado y sella la cuticula: ayuda a reducir la caida y estimula el crecimiento saludable desde la raiz. | Y78: Facilita el desenredado | Sella la cuticula | Aporta suavidad y brillo | AA78: Acondicionador | AC78: Aplicar en el largo y las puntas del cabello despues del champu, dejar actuar unos minutos y enjuagar. | AD78: Extrato de jaborandi | Extrato de nogueira | Extrato de arruda | AE78: Extracto de jaborandi | Extracto de nogal | Extracto de ruda | AH78: condicionador-jaborandi-antiqueda-300ml.webp | AJ78: Cabello con caida, cabello graso o debilitado | AK78: https://haskellcosmeticos.com.br/tratamentos-capilares/linha-jaborandi-haskell/ | AL78: 2026-07-24 | AM78: =IF(ISBLANK(Q78),"",Q78*Parametros_PEN!$B$2) | AN78: =IF(ISBLANK(Q78),"",Q78*Parametros_PEN!$B$2*(1+Parametros_PEN!$B$3)) | AO78: =IF(ISBLANK(R78),"",R78*Parametros_PEN!$B$2) | AP78: =IF(ISBLANK(R78),"",R78*Parametros_PEN!$B$2*(1+Parametros_PEN!$B$3))
A79: HSK-0078 | B79: acondicionador-jaborandi-anticaida-500-ml | D79: Haskell | E79: Condicionador Jaborandi Antiqueda 500ml | F79: Acondicionador Jaborandi Anticaida 500 ml | G79: Jaborandi Antiqueda | H79: Tratamentos Capilares | I79: Tratamientos capilares | J79: Anti-queda | K79: Anticaida | L79: Condicionador | M79: Acondicionador | N79: 500 ml | O79: 500 | P79: ml | Q79: 76.9 | S79: =IF(ISBLANK(R79),0,IFERROR((Q79-R79)/Q79,0)) | T79: =R79<>"" | U79: =TRUE() | W79: Acondicionador de la linea Jaborandi Antiqueda que facilita el desenredado y sella la cuticula: ayuda a reducir la caida y estimula el crecimiento saludable desde la raiz. | Y79: Facilita el desenredado | Sella la cuticula | Aporta suavidad y brillo | AA79: Acondicionador | AC79: Aplicar en el largo y las puntas del cabello despues del champu, dejar actuar unos minutos y enjuagar. | AD79: Extrato de jaborandi | Extrato de nogueira | Extrato de arruda | AE79: Extracto de jaborandi | Extracto de nogal | Extracto de ruda | AH79: condicionador-jaborandi-antiqueda-500ml.webp | AJ79: Cabello con caida, cabello graso o debilitado | AK79: https://haskellcosmeticos.com.br/tratamentos-capilares/linha-jaborandi-haskell/ | AL79: 2026-07-24 | AM79: =IF(ISBLANK(Q79),"",Q79*Parametros_PEN!$B$2) | AN79: =IF(ISBLANK(Q79),"",Q79*Parametros_PEN!$B$2*(1+Parametros_PEN!$B$3)) | AO79: =IF(ISBLANK(R79),"",R79*Parametros_PEN!$B$2) | AP79: =IF(ISBLANK(R79),"",R79*Parametros_PEN!$B$2*(1+Parametros_PEN!$B$3))
A80: HSK-0079 | B80: tonico-fortalecedor-jaborandi-anticaida-120-ml | D80: Haskell | E80: Tonico Fortalecedor Jaborandi Antiqueda 120ml | F80: Tonico fortalecedor Jaborandi Anticaida 120 ml | G80: Jaborandi Antiqueda | H80: Tratamentos Capilares | I80: Tratamientos capilares | J80: Anti-queda | K80: Anticaida | L80: Tonico | M80: Tonico capilar | N80: 120 ml | O80: 120 | P80: ml | Q80: 48.9 | S80: =IF(ISBLANK(R80),0,IFERROR((Q80-R80)/Q80,0)) | T80: =R80<>"" | U80: =TRUE() | W80: Tonico capilar de la linea Jaborandi Antiqueda, de uso directo sobre el cuero cabelludo: ayuda a reducir la caida y estimula el crecimiento saludable desde la raiz. | Y80: Estimula el cuero cabelludo | Refuerza la raiz del cabello | AA80: Tonico capilar | AC80: Aplicar directamente sobre el cuero cabelludo limpio y masajear suavemente. No es necesario enjuagar. | AD80: Extrato de jaborandi | Extrato de nogueira | Extrato de arruda | AE80: Extracto de jaborandi | Extracto de nogal | Extracto de ruda | AH80: tonico-fortalecedor-jaborandi-antiqueda-120ml.webp | AJ80: Cabello con caida, cabello graso o debilitado | AK80: https://haskellcosmeticos.com.br/tratamentos-capilares/linha-jaborandi-haskell/ | AL80: 2026-07-24 | AM80: =IF(ISBLANK(Q80),"",Q80*Parametros_PEN!$B$2) | AN80: =IF(ISBLANK(Q80),"",Q80*Parametros_PEN!$B$2*(1+Parametros_PEN!$B$3)) | AO80: =IF(ISBLANK(R80),"",R80*Parametros_PEN!$B$2) | AP80: =IF(ISBLANK(R80),"",R80*Parametros_PEN!$B$2*(1+Parametros_PEN!$B$3))
A81: HSK-0080 | B81: nectavita-jaborandi-anticaida-35-ml | D81: Haskell | E81: Nectavita Jaborandi Antiqueda 35ml | F81: Nectavita Jaborandi Anticaida 35 ml | G81: Jaborandi Antiqueda | H81: Tratamentos Capilares | I81: Tratamientos capilares | J81: Anti-queda | K81: Anticaida | L81: Nectavita | M81: Potenciador pre-champu | N81: 35 ml | O81: 35 | P81: ml | Q81: 25.9 | S81: =IF(ISBLANK(R81),0,IFERROR((Q81-R81)/Q81,0)) | T81: =R81<>"" | U81: =TRUE() | W81: Potenciador pre-champu (nectavita) de la linea Jaborandi Antiqueda, para usar antes del lavado: ayuda a reducir la caida y estimula el crecimiento saludable desde la raiz. | Y81: Prepara el cuero cabelludo antes del champu | Potencia el efecto del tratamiento | AA81: Pre-champu | AC81: Aplicar sobre el cuero cabelludo antes del champu, masajear y proceder con el lavado habitual. | AD81: Extrato de jaborandi | Extrato de nogueira | Extrato de arruda | AE81: Extracto de jaborandi | Extracto de nogal | Extracto de ruda | AH81: nectavita-jaborandi-antiqueda-35ml.webp | AJ81: Cabello con caida, cabello graso o debilitado | AK81: https://haskellcosmeticos.com.br/tratamentos-capilares/linha-jaborandi-haskell/ | AL81: 2026-07-24 | AM81: =IF(ISBLANK(Q81),"",Q81*Parametros_PEN!$B$2) | AN81: =IF(ISBLANK(Q81),"",Q81*Parametros_PEN!$B$2*(1+Parametros_PEN!$B$3)) | AO81: =IF(ISBLANK(R81),"",R81*Parametros_PEN!$B$2) | AP81: =IF(ISBLANK(R81),"",R81*Parametros_PEN!$B$2*(1+Parametros_PEN!$B$3))
... A101: HSK-0100 | B101: finalizador-fortalecedor-ora-pro-nobis-120-ml | D101: Haskell | E101: Finalizador Fortalecedor Ora-Pro-Nobis 120ml | F101: Finalizador fortalecedor Ora-pro-nobis 120 ml | G101: Ora-pro-nobis | H101: Tratamentos Capilares | I101: Tratamientos capilares | J101: Forca extrema | K101: Fuerza extrema | L101: Finalizador | M101: Finalizador | N101: 120 ml | O101: 120 | P101: ml | Q101: 48.9 | S101: =IF(ISBLANK(R101),0,IFERROR((Q101-R101)/Q101,0)) | T101: =R101<>"" | U101: =TRUE() | W101: Finalizador sin enjuague de la linea Ora-pro-nobis: fortalece intensamente la fibra capilar y ayuda a prevenir la quiebre en cabello debil. | Y101: Facilita el peinado | Protege del calor y de agresiones externas | AA101: Finalizador | AC101: Aplicar sobre el cabello limpio y humedo, distribuir en todo el largo. | AD101: Extrato de ora-pro-nobis | AE101: Extracto de ora-pro-nobis | AH101: finalizador-fortalecedor-ora-pro-nobis-120ml.webp | AJ101: Cabello debil, fino o quebradizo | AK101: https://haskellcosmeticos.com.br/tratamentos-capilares/linha-ora-pro-nobis-haskell/ | AL101: 2026-07-24 | AM101: =IF(ISBLANK(Q101),"",Q101*Parametros_PEN!$B$2) | AN101: =IF(ISBLANK(Q101),"",Q101*Parametros_PEN!$B$2*(1+Parametros_PEN!$B$3)) | AO101: =IF(ISBLANK(R101),"",R101*Parametros_PEN!$B$2) | AP101: =IF(ISBLANK(R101),"",R101*Parametros_PEN!$B$2*(1+Parametros_PEN!$B$3))
A102: HSK-0101 | B102: fluido-capilar-pre-entreno-200-ml | D102: Haskell | E102: Fluido Capilar Pre-Treino 200ml | F102: Fluido capilar Pre-entreno 200 ml | G102: Pre-Treino | H102: Tratamentos Capilares | I102: Tratamientos capilares | J102: Protecao para atividade fisica | K102: Proteccion para actividad fisica | L102: Fluido | M102: Fluido finalizador | N102: 200 ml | O102: 200 | P102: ml | Q102: 59.9 | S102: =IF(ISBLANK(R102),0,IFERROR((Q102-R102)/Q102,0)) | T102: =R102<>"" | U102: =TRUE() | W102: Fluido finalizador sin enjuague de la linea Pre-Treino: protege el cabello del sudor, el frizz y la exposicion solar durante el ejercicio. | Y102: Finalizador sin enjuague | Facilita el peinado | Protege del calor y de agresiones externas | AA102: Finalizador | AC102: Aplicar sobre el cabello limpio y humedo, distribuir en todo el largo y finalizar como se prefiera. | AD102: Vitamina E | Cera de arroz | AE102: Vitamina E | Cera de arroz | AH102: fluido-capilar-pre-treino.webp | AI102: fluido-capilar-pre-treino_02.webp | AJ102: Personas que entrenan con frecuencia y exponen el cabello al sudor | AK102: https://haskellcosmeticos.com.br/tratamentos-capilares/pre-treino/ | AL102: 2026-07-24 | AM102: =IF(ISBLANK(Q102),"",Q102*Parametros_PEN!$B$2) | AN102: =IF(ISBLANK(Q102),"",Q102*Parametros_PEN!$B$2*(1+Parametros_PEN!$B$3)) | AO102: =IF(ISBLANK(R102),"",R102*Parametros_PEN!$B$2) | AP102: =IF(ISBLANK(R102),"",R102*Parametros_PEN!$B$2*(1+Parametros_PEN!$B$3))
A103: HSK-0102 | B103: champu-posprogresiva-300-ml | D103: Haskell | E103: Shampoo Pos-Progressiva 300ml | F103: Champu Posprogresiva 300 ml | G103: Pos-Progressiva | H103: Tratamentos Capilares | I103: Tratamientos capilares | J103: Manutencao do alisamento | K103: Mantenimiento de alisado | L103: Shampoo | M103: Champu | N103: 300 ml | O103: 300 | P103: ml | Q103: 62.9 | S103: =IF(ISBLANK(R103),0,IFERROR((Q103-R103)/Q103,0)) | T103: =R103<>"" | U103: =TRUE() | W103: Champu de limpieza suave de la linea Pos-Progressiva, que prepara el cabello para el tratamiento: ayuda a mantener el efecto del alisado progresivo por mas tiempo. | Y103: Limpieza suave sin resecar | Prepara el cabello para el resto de la rutina | Respeta el equilibrio del cuero cabelludo | AA103: Limpiador suave | AC103: Aplicar sobre el cabello mojado, masajear el cuero cabelludo con movimientos suaves y enjuagar bien. | AH103: shampoo-pos-progressiva-haskell-300ml.webp | AJ103: Cabello con alisado progresivo reciente | AK103: https://haskellcosmeticos.com.br/tratamentos-capilares/linha-pos-progressiva-haskell/ | AL103: 2026-07-24 | AM103: =IF(ISBLANK(Q103),"",Q103*Parametros_PEN!$B$2) | AN103: =IF(ISBLANK(Q103),"",Q103*Parametros_PEN!$B$2*(1+Parametros_PEN!$B$3)) | AO103: =IF(ISBLANK(R103),"",R103*Parametros_PEN!$B$2) | AP103: =IF(ISBLANK(R103),"",R103*Parametros_PEN!$B$2*(1+Parametros_PEN!$B$3))
A104: HSK-0103 | B104: champu-posprogresiva-500-ml | D104: Haskell | E104: Shampoo Pos-Progressiva 500ml | F104: Champu Posprogresiva 500 ml | G104: Pos-Progressiva | H104: Tratamentos Capilares | I104: Tratamientos capilares | J104: Manutencao do alisamento | K104: Mantenimiento de alisado | L104: Shampoo | M104: Champu | N104: 500 ml | O104: 500 | P104: ml | Q104: 84.9 | S104: =IF(ISBLANK(R104),0,IFERROR((Q104-R104)/Q104,0)) | T104: =R104<>"" | U104: =TRUE() | W104: Champu de limpieza suave de la linea Pos-Progressiva, que prepara el cabello para el tratamiento: ayuda a mantener el efecto del alisado progresivo por mas tiempo. | Y104: Limpieza suave sin resecar | Prepara el cabello para el resto de la rutina | Respeta el equilibrio del cuero cabelludo | AA104: Limpiador suave | AC104: Aplicar sobre el cabello mojado, masajear el cuero cabelludo con movimientos suaves y enjuagar bien. | AH104: shampoo-pos-progressiva-500ml.webp | AJ104: Cabello con alisado progresivo reciente | AK104: https://haskellcosmeticos.com.br/tratamentos-capilares/linha-pos-progressiva-haskell/ | AL104: 2026-07-24 | AM104: =IF(ISBLANK(Q104),"",Q104*Parametros_PEN!$B$2) | AN104: =IF(ISBLANK(Q104),"",Q104*Parametros_PEN!$B$2*(1+Parametros_PEN!$B$3)) | AO104: =IF(ISBLANK(R104),"",R104*Parametros_PEN!$B$2) | AP104: =IF(ISBLANK(R104),"",R104*Parametros_PEN!$B$2*(1+Parametros_PEN!$B$3))
A105: HSK-0104 | B105: acondicionador-posprogresiva-300-ml | D105: Haskell | E105: Condicionador Pos-Progressiva 300ml | F105: Acondicionador Posprogresiva 300 ml | G105: Pos-Progressiva | H105: Tratamentos Capilares | I105: Tratamientos capilares | J105: Manutencao do alisamento | K105: Mantenimiento de alisado | L105: Condicionador | M105: Acondicionador | N105: 300 ml | O105: 300 | P105: ml | Q105: 62.9 | S105: =IF(ISBLANK(R105),0,IFERROR((Q105-R105)/Q105,0)) | T105: =R105<>"" | U105: =TRUE() | W105: Acondicionador de la linea Pos-Progressiva que facilita el desenredado y sella la cuticula: ayuda a mantener el efecto del alisado progresivo por mas tiempo. | Y105: Facilita el desenredado | Sella la cuticula | Aporta suavidad y brillo | AA105: Acondicionador | AC105: Aplicar en el largo y las puntas del cabello despues del champu, dejar actuar unos minutos y enjuagar. | AH105: condicionador-pos-progressiva-haskell-300ml.webp | AJ105: Cabello con alisado progresivo reciente | AK105: https://haskellcosmeticos.com.br/tratamentos-capilares/linha-pos-progressiva-haskell/ | AL105: 2026-07-24 | AM105: =IF(ISBLANK(Q105),"",Q105*Parametros_PEN!$B$2) | AN105: =IF(ISBLANK(Q105),"",Q105*Parametros_PEN!$B$2*(1+Parametros_PEN!$B$3)) | AO105: =IF(ISBLANK(R105),"",R105*Parametros_PEN!$B$2) | AP105: =IF(ISBLANK(R105),"",R105*Parametros_PEN!$B$2*(1+Parametros_PEN!$B$3))
A106: HSK-0105 | B106: acondicionador-posprogresiva-500-ml | D106: Haskell | E106: Condicionador Pos-Progressiva 500ml | F106: Acondicionador Posprogresiva 500 ml | G106: Pos-Progressiva | H106: Tratamentos Capilares | I106: Tratamientos capilares | J106: Manutencao do alisamento | K106: Mantenimiento de alisado | L106: Condicionador | M106: Acondicionador | N106: 500 ml | O106: 500 | P106: ml | Q106: 84.9 | S106: =IF(ISBLANK(R106),0,IFERROR((Q106-R106)/Q106,0)) | T106: =R106<>"" | U106: =TRUE() | W106: Acondicionador de la linea Pos-Progressiva que facilita el desenredado y sella la cuticula: ayuda a mantener el efecto del alisado progresivo por mas tiempo. | Y106: Facilita el desenredado | Sella la cuticula | Aporta suavidad y brillo | AA106: Acondicionador | AC106: Aplicar en el largo y las puntas del cabello despues del champu, dejar actuar unos minutos y enjuagar. | AH106: condicionador-pos-progressiva-haskell-500ml.webp | AJ106: Cabello con alisado progresivo reciente | AK106: https://haskellcosmeticos.com.br/tratamentos-capilares/linha-pos-progressiva-haskell/ | AL106: 2026-07-24 | AM106: =IF(ISBLANK(Q106),"",Q106*Parametros_PEN!$B$2) | AN106: =IF(ISBLANK(Q106),"",Q106*Parametros_PEN!$B$2*(1+Parametros_PEN!$B$3)) | AO106: =IF(ISBLANK(R106),"",R106*Parametros_PEN!$B$2) | AP106: =IF(ISBLANK(R106),"",R106*Parametros_PEN!$B$2*(1+Parametros_PEN!$B$3))
A107: HSK-0106 | B107: mascarilla-de-tratamiento-posprogresiva-300-g | D107: Haskell | E107: Mascara de Tratamento Pos-Progressiva 300g | F107: Mascarilla de tratamiento Posprogresiva 300 g | G107: Pos-Progressiva | H107: Tratamentos Capilares | I107: Tratamientos capilares | J107: Manutencao do alisamento | K107: Mantenimiento de alisado | L107: Mascara de Tratamento | M107: Mascarilla de tratamiento | N107: 300 g | O107: 300 | P107: g | Q107: 74.9 | S107: =IF(ISBLANK(R107),0,IFERROR((Q107-R107)/Q107,0)) | T107: =R107<>"" | U107: =TRUE() | W107: Mascarilla de tratamiento concentrada de la linea Pos-Progressiva, de uso posterior al champu: ayuda a mantener el efecto del alisado progresivo por mas tiempo. | Y107: Tratamiento concentrado | Actua en profundidad sobre la fibra capilar | Refuerza el resultado de la linea | AA107: Tratamiento intensivo | AC107: Aplicar mechon por mechon despues del champu, dejar actuar de 3 a 5 minutos y enjuagar bien. | AH107: mascara-de-tratamento-pos-progressiva-300g-kxuj9.webp | AJ107: Cabello con alisado progresivo reciente | AK107: https://haskellcosmeticos.com.br/tratamentos-capilares/linha-pos-progressiva-haskell/ | AL107: 2026-07-24 | AM107: =IF(ISBLANK(Q107),"",Q107*Parametros_PEN!$B$2) | AN107: =IF(ISBLANK(Q107),"",Q107*Parametros_PEN!$B$2*(1+Parametros_PEN!$B$3)) | AO107: =IF(ISBLANK(R107),"",R107*Parametros_PEN!$B$2) | AP107: =IF(ISBLANK(R107),"",R107*Parametros_PEN!$B$2*(1+Parametros_PEN!$B$3))
A108: HSK-0107 | B108: mascarilla-de-tratamiento-posprogresiva-500-g | D108: Haskell | E108: Mascara de Tratamento Pos-Progressiva 500g | F108: Mascarilla de tratamiento Posprogresiva 500 g | G108: Pos-Progressiva | H108: Tratamentos Capilares | I108: Tratamientos capilares | J108: Manutencao do alisamento | K108: Mantenimiento de alisado | L108: Mascara de Tratamento | M108: Mascarilla de tratamiento | N108: 500 g | O108: 500 | P108: g | Q108: 89.9 | S108: =IF(ISBLANK(R108),0,IFERROR((Q108-R108)/Q108,0)) | T108: =R108<>"" | U108: =TRUE() | W108: Mascarilla de tratamiento concentrada de la linea Pos-Progressiva, de uso posterior al champu: ayuda a mantener el efecto del alisado progresivo por mas tiempo. | Y108: Tratamiento concentrado | Actua en profundidad sobre la fibra capilar | Refuerza el resultado de la linea | AA108: Tratamiento intensivo | AC108: Aplicar mechon por mechon despues del champu, dejar actuar de 3 a 5 minutos y enjuagar bien. | AH108: mascara-de-tratamento-pos-progressiva-500g-e3859.webp | AJ108: Cabello con alisado progresivo reciente | AK108: https://haskellcosmeticos.com.br/tratamentos-capilares/linha-pos-progressiva-haskell/ | AL108: 2026-07-24 | AM108: =IF(ISBLANK(Q108),"",Q108*Parametros_PEN!$B$2) | AN108: =IF(ISBLANK(Q108),"",Q108*Parametros_PEN!$B$2*(1+Parametros_PEN!$B$3)) | AO108: =IF(ISBLANK(R108),"",R108*Parametros_PEN!$B$2) | AP108: =IF(ISBLANK(R108),"",R108*Parametros_PEN!$B$2*(1+Parametros_PEN!$B$3))
A109: HSK-0108 | B109: fluido-alineador-posprogresiva-120-ml | D109: Haskell | E109: Fluido Alinhador Pos-Progressiva 120ml | F109: Fluido alineador Posprogresiva 120 ml | G109: Pos-Progressiva | H109: Tratamentos Capilares | I109: Tratamientos capilares | J109: Manutencao do alisamento | K109: Mantenimiento de alisado | L109: Fluido | M109: Fluido finalizador | N109: 120 ml | O109: 120 | P109: ml | Q109: 48.9 | S109: =IF(ISBLANK(R109),0,IFERROR((Q109-R109)/Q109,0)) | T109: =R109<>"" | U109: =TRUE() | W109: Fluido finalizador sin enjuague de la linea Pos-Progressiva: ayuda a mantener el efecto del alisado progresivo por mas tiempo. | Y109: Finalizador sin enjuague | Facilita el peinado | Protege del calor y de agresiones externas | AA109: Finalizador | AC109: Aplicar sobre el cabello limpio y humedo, distribuir en todo el largo y finalizar como se prefiera. | AH109: fluido-alinhador-pos-progressiva-120ml-1vk6k.webp | AJ109: Cabello con alisado progresivo reciente | AK109: https://haskellcosmeticos.com.br/tratamentos-capilares/linha-pos-progressiva-haskell/ | AL109: 2026-07-24 | AM109: =IF(ISBLANK(Q109),"",Q109*Parametros_PEN!$B$2) | AN109: =IF(ISBLANK(Q109),"",Q109*Parametros_PEN!$B$2*(1+Parametros_PEN!$B$3)) | AO109: =IF(ISBLANK(R109),"",R109*Parametros_PEN!$B$2) | AP109: =IF(ISBLANK(R109),"",R109*Parametros_PEN!$B$2*(1+Parametros_PEN!$B$3))
A110: HSK-0109 | B110: mascarilla-de-tratamiento-queratina-provit-b5-300-g | D110: Haskell | E110: Mascara de Tratamento Queratina & Provit B5 300g | F110: Mascarilla de tratamiento Queratina & Provit B5 300 g | G110: Queratina & Provit B5 | H110: Tratamentos Capilares | I110: Tratamientos capilares | J110: Reconstrucao proteica | K110: Reconstruccion proteica | L110: Mascara de Tratamento | M110: Mascarilla de tratamiento | N110: 300 g | O110: 300 | P110: g | Q110: 68.9 | S110: =IF(ISBLANK(R110),0,IFERROR((Q110-R110)/Q110,0)) | T110: =R110<>"" | U110: =TRUE() | W110: Mascarilla de tratamiento concentrada de la linea Queratina & Provit B5, de uso posterior al champu: repone masa proteica y reconstruye la fibra capilar danada. | Y110: Tratamiento concentrado | Actua en profundidad sobre la fibra capilar | Refuerza el resultado de la linea | AA110: Tratamiento intensivo | AC110: Aplicar mechon por mechon despues del champu, dejar actuar de 3 a 5 minutos y enjuagar bien. | AD110: Queratina vegetal | Pro-vitamina B5 (D-pantenol) | AE110: Queratina vegetal | Pro-vitamina B5 (D-pantenol) | AH110: mascara-de-tratamento-queratina-provit-b5-300g.webp | AJ110: Cabello danado por procesos quimicos, termicos o mecanicos | AK110: https://haskellcosmeticos.com.br/tratamentos-capilares/linha-queratina-haskell/ | AL110: 2026-07-24 | AM110: =IF(ISBLANK(Q110),"",Q110*Parametros_PEN!$B$2) | AN110: =IF(ISBLANK(Q110),"",Q110*Parametros_PEN!$B$2*(1+Parametros_PEN!$B$3)) | AO110: =IF(ISBLANK(R110),"",R110*Parametros_PEN!$B$2) | AP110: =IF(ISBLANK(R110),"",R110*Parametros_PEN!$B$2*(1+Parametros_PEN!$B$3))
A111: HSK-0110 | B111: champu-quina-rosa-300-ml | D111: Haskell | E111: Shampoo Quina Rosa 300ml | F111: Champu Quina Rosa 300 ml | G111: Quina Rosa | H111: Tratamentos Capilares | I111: Tratamientos capilares | J111: Brilho e controle de frizz | K111: Brillo y control de frizz | L111: Shampoo | M111: Champu | N111: 300 ml | O111: 300 | P111: ml | Q111: 58.9 | S111: =IF(ISBLANK(R111),0,IFERROR((Q111-R111)/Q111,0)) | T111: =R111<>"" | U111: =TRUE() | W111: Champu de limpieza suave de la linea Quina Rosa, que prepara el cabello para el tratamiento: revitaliza el cabello opaco, reduce el frizz y aporta brillo. | Y111: Limpieza suave sin resecar | Prepara el cabello para el resto de la rutina | Respeta el equilibrio del cuero cabelludo | AA111: Limpiador suave | AC111: Aplicar sobre el cabello mojado, masajear el cuero cabelludo con movimientos suaves y enjuagar bien. | AD111: Extrato de quina rosa | AE111: Extracto de quina rosa | AH111: shampoo-quina-rosa-haskell-300ml.webp | AJ111: Cabello opaco, con frizz o sin vida | AK111: https://haskellcosmeticos.com.br/tratamentos-capilares/linha-quina-rosa-haskell/ | AL111: 2026-07-24 | AM111: =IF(ISBLANK(Q111),"",Q111*Parametros_PEN!$B$2) | AN111: =IF(ISBLANK(Q111),"",Q111*Parametros_PEN!$B$2*(1+Parametros_PEN!$B$3)) | AO111: =IF(ISBLANK(R111),"",R111*Parametros_PEN!$B$2) | AP111: =IF(ISBLANK(R111),"",R111*Parametros_PEN!$B$2*(1+Parametros_PEN!$B$3))
A112: HSK-0111 | B112: champu-quina-rosa-500-ml | D112: Haskell | E112: Shampoo Quina Rosa 500ml | F112: Champu Quina Rosa 500 ml | G112: Quina Rosa | H112: Tratamentos Capilares | I112: Tratamientos capilares | J112: Brilho e controle de frizz | K112: Brillo y control de frizz | L112: Shampoo | M112: Champu | N112: 500 ml | O112: 500 | P112: ml | Q112: 76.9 | S112: =IF(ISBLANK(R112),0,IFERROR((Q112-R112)/Q112,0)) | T112: =R112<>"" | U112: =TRUE() | W112: Champu de limpieza suave de la linea Quina Rosa, que prepara el cabello para el tratamiento: revitaliza el cabello opaco, reduce el frizz y aporta brillo. | Y112: Limpieza suave sin resecar | Prepara el cabello para el resto de la rutina | Respeta el equilibrio del cuero cabelludo | AA112: Limpiador suave | AC112: Aplicar sobre el cabello mojado, masajear el cuero cabelludo con movimientos suaves y enjuagar bien. | AD112: Extrato de quina rosa | AE112: Extracto de quina rosa | AH112: shampoo-quina-rosa-haskell-500ml.webp | AJ112: Cabello opaco, con frizz o sin vida | AK112: https://haskellcosmeticos.com.br/tratamentos-capilares/linha-quina-rosa-haskell/ | AL112: 2026-07-24 | AM112: =IF(ISBLANK(Q112),"",Q112*Parametros_PEN!$B$2) | AN112: =IF(ISBLANK(Q112),"",Q112*Parametros_PEN!$B$2*(1+Parametros_PEN!$B$3)) | AO112: =IF(ISBLANK(R112),"",R112*Parametros_PEN!$B$2) | AP112: =IF(ISBLANK(R112),"",R112*Parametros_PEN!$B$2*(1+Parametros_PEN!$B$3))
A113: HSK-0112 | B113: champu-quina-rosa-1-l | D113: Haskell | E113: Shampoo Quina Rosa 1L | F113: Champu Quina Rosa 1 L | G113: Quina Rosa | H113: Tratamentos Capilares | I113: Tratamientos capilares | J113: Brilho e controle de frizz | K113: Brillo y control de frizz | L113: Shampoo | M113: Champu | N113: 1000 ml | O113: 1000 | P113: ml | Q113: 118.9 | S113: =IF(ISBLANK(R113),0,IFERROR((Q113-R113)/Q113,0)) | T113: =R113<>"" | U113: =TRUE() | W113: Champu de limpieza suave de la linea Quina Rosa, que prepara el cabello para el tratamiento: revitaliza el cabello opaco, reduce el frizz y aporta brillo. | Y113: Limpieza suave sin resecar | Prepara el cabello para el resto de la rutina | Respeta el equilibrio del cuero cabelludo | AA113: Limpiador suave | AC113: Aplicar sobre el cabello mojado, masajear el cuero cabelludo con movimientos suaves y enjuagar bien. | AD113: Extrato de quina rosa | AE113: Extracto de quina rosa | AH113: shampoo-quina-rosa-haskell-1l.webp | AJ113: Cabello opaco, con frizz o sin vida | AK113: https://haskellcosmeticos.com.br/tratamentos-capilares/linha-quina-rosa-haskell/ | AL113: 2026-07-24 | AM113: =IF(ISBLANK(Q113),"",Q113*Parametros_PEN!$B$2) | AN113: =IF(ISBLANK(Q113),"",Q113*Parametros_PEN!$B$2*(1+Parametros_PEN!$B$3)) | AO113: =IF(ISBLANK(R113),"",R113*Parametros_PEN!$B$2) | AP113: =IF(ISBLANK(R113),"",R113*Parametros_PEN!$B$2*(1+Parametros_PEN!$B$3))
A114: HSK-0113 | B114: acondicionador-quina-rosa-300-ml | D114: Haskell | E114: Condicionador Quina Rosa 300ml | F114: Acondicionador Quina Rosa 300 ml | G114: Quina Rosa | H114: Tratamentos Capilares | I114: Tratamientos capilares | J114: Brilho e controle de frizz | K114: Brillo y control de frizz | L114: Condicionador | M114: Acondicionador | N114: 300 ml | O114: 300 | P114: ml | Q114: 58.9 | S114: =IF(ISBLANK(R114),0,IFERROR((Q114-R114)/Q114,0)) | T114: =R114<>"" | U114: =TRUE() | W114: Acondicionador de la linea Quina Rosa que facilita el desenredado y sella la cuticula: revitaliza el cabello opaco, reduce el frizz y aporta brillo. | Y114: Facilita el desenredado | Sella la cuticula | Aporta suavidad y brillo | AA114: Acondicionador | AC114: Aplicar en el largo y las puntas del cabello despues del champu, dejar actuar unos minutos y enjuagar. | AD114: Extrato de quina rosa | AE114: Extracto de quina rosa | AH114: condicionador-quina-rosa-haskell-300ml.webp | AJ114: Cabello opaco, con frizz o sin vida | AK114: https://haskellcosmeticos.com.br/tratamentos-capilares/linha-quina-rosa-haskell/ | AL114: 2026-07-24 | AM114: =IF(ISBLANK(Q114),"",Q114*Parametros_PEN!$B$2) | AN114: =IF(ISBLANK(Q114),"",Q114*Parametros_PEN!$B$2*(1+Parametros_PEN!$B$3)) | AO114: =IF(ISBLANK(R114),"",R114*Parametros_PEN!$B$2) | AP114: =IF(ISBLANK(R114),"",R114*Parametros_PEN!$B$2*(1+Parametros_PEN!$B$3))
A115: HSK-0114 | B115: acondicionador-quina-rosa-500-ml | D115: Haskell | E115: Condicionador Quina Rosa 500ml | F115: Acondicionador Quina Rosa 500 ml | G115: Quina Rosa | H115: Tratamentos Capilares | I115: Tratamientos capilares | J115: Brilho e controle de frizz | K115: Brillo y control de frizz | L115: Condicionador | M115: Acondicionador | N115: 500 ml | O115: 500 | P115: ml | Q115: 76.9 | S115: =IF(ISBLANK(R115),0,IFERROR((Q115-R115)/Q115,0)) | T115: =R115<>"" | U115: =TRUE() | W115: Acondicionador de la linea Quina Rosa que facilita el desenredado y sella la cuticula: revitaliza el cabello opaco, reduce el frizz y aporta brillo. | Y115: Facilita el desenredado | Sella la cuticula | Aporta suavidad y brillo | AA115: Acondicionador | AC115: Aplicar en el largo y las puntas del cabello despues del champu, dejar actuar unos minutos y enjuagar. | AD115: Extrato de quina rosa | AE115: Extracto de quina rosa | AH115: condicionador-quina-rosa-500ml.webp | AJ115: Cabello opaco, con frizz o sin vida | AK115: https://haskellcosmeticos.com.br/tratamentos-capilares/linha-quina-rosa-haskell/ | AL115: 2026-07-24 | AM115: =IF(ISBLANK(Q115),"",Q115*Parametros_PEN!$B$2) | AN115: =IF(ISBLANK(Q115),"",Q115*Parametros_PEN!$B$2*(1+Parametros_PEN!$B$3)) | AO115: =IF(ISBLANK(R115),"",R115*Parametros_PEN!$B$2) | AP115: =IF(ISBLANK(R115),"",R115*Parametros_PEN!$B$2*(1+Parametros_PEN!$B$3))
A116: HSK-0115 | B116: mascarilla-de-tratamiento-quina-rosa-300-g | D116: Haskell | E116: Mascara de Tratamento Quina Rosa 300g | F116: Mascarilla de tratamiento Quina Rosa 300 g | G116: Quina Rosa | H116: Tratamentos Capilares | I116: Tratamientos capilares | J116: Brilho e controle de frizz | K116: Brillo y control de frizz | L116: Mascara de Tratamento | M116: Mascarilla de tratamiento | N116: 300 g | O116: 300 | P116: g | Q116: 68.9 | S116: =IF(ISBLANK(R116),0,IFERROR((Q116-R116)/Q116,0)) | T116: =R116<>"" | U116: =TRUE() | W116: Mascarilla de tratamiento concentrada de la linea Quina Rosa, de uso posterior al champu: revitaliza el cabello opaco, reduce el frizz y aporta brillo. | Y116: Tratamiento concentrado | Actua en profundidad sobre la fibra capilar | Refuerza el resultado de la linea | AA116: Tratamiento intensivo | AC116: Aplicar mechon por mechon despues del champu, dejar actuar de 3 a 5 minutos y enjuagar bien. | AD116: Extrato de quina rosa | AE116: Extracto de quina rosa | AH116: mascara-de-tratamento-quina-rosa-300g.webp | AJ116: Cabello opaco, con frizz o sin vida | AK116: https://haskellcosmeticos.com.br/tratamentos-capilares/linha-quina-rosa-haskell/ | AL116: 2026-07-24 | AM116: =IF(ISBLANK(Q116),"",Q116*Parametros_PEN!$B$2) | AN116: =IF(ISBLANK(Q116),"",Q116*Parametros_PEN!$B$2*(1+Parametros_PEN!$B$3)) | AO116: =IF(ISBLANK(R116),"",R116*Parametros_PEN!$B$2) | AP116: =IF(ISBLANK(R116),"",R116*Parametros_PEN!$B$2*(1+Parametros_PEN!$B$3))
A117: HSK-0116 | B117: mascarilla-de-tratamiento-quina-rosa-500-g | D117: Haskell | E117: Mascara de Tratamento Quina Rosa 500g | F117: Mascarilla de tratamiento Quina Rosa 500 g | G117: Quina Rosa | H117: Tratamentos Capilares | I117: Tratamientos capilares | J117: Brilho e controle de frizz | K117: Brillo y control de frizz | L117: Mascara de Tratamento | M117: Mascarilla de tratamiento | N117: 500 g | O117: 500 | P117: g | Q117: 81.9 | S117: =IF(ISBLANK(R117),0,IFERROR((Q117-R117)/Q117,0)) | T117: =R117<>"" | U117: =TRUE() | W117: Mascarilla de tratamiento concentrada de la linea Quina Rosa, de uso posterior al champu: revitaliza el cabello opaco, reduce el frizz y aporta brillo. | Y117: Tratamiento concentrado | Actua en profundidad sobre la fibra capilar | Refuerza el resultado de la linea | AA117: Tratamiento intensivo | AC117: Aplicar mechon por mechon despues del champu, dejar actuar de 3 a 5 minutos y enjuagar bien. | AD117: Extrato de quina rosa | AE117: Extracto de quina rosa | AH117: mascara-de-tratamento-quina-rosa-500g.webp | AJ117: Cabello opaco, con frizz o sin vida | AK117: https://haskellcosmeticos.com.br/tratamentos-capilares/linha-quina-rosa-haskell/ | AL117: 2026-07-24 | AM117: =IF(ISBLANK(Q117),"",Q117*Parametros_PEN!$B$2) | AN117: =IF(ISBLANK(Q117),"",Q117*Parametros_PEN!$B$2*(1+Parametros_PEN!$B$3)) | AO117: =IF(ISBLANK(R117),"",R117*Parametros_PEN!$B$2) | AP117: =IF(ISBLANK(R117),"",R117*Parametros_PEN!$B$2*(1+Parametros_PEN!$B$3))
A118: HSK-0117 | B118: mascarilla-de-tratamiento-quina-rosa-900-g | D118: Haskell | E118: Mascara de Tratamento Quina Rosa 900g | F118: Mascarilla de tratamiento Quina Rosa 900 g | G118: Quina Rosa | H118: Tratamentos Capilares | I118: Tratamientos capilares | J118: Brilho e controle de frizz | K118: Brillo y control de frizz | L118: Mascara de Tratamento | M118: Mascarilla de tratamiento | N118: 900 g | O118: 900 | P118: g | Q118: 123.9 | S118: =IF(ISBLANK(R118),0,IFERROR((Q118-R118)/Q118,0)) | T118: =R118<>"" | U118: =TRUE() | W118: Mascarilla de tratamiento concentrada de la linea Quina Rosa, de uso posterior al champu: revitaliza el cabello opaco, reduce el frizz y aporta brillo. | Y118: Tratamiento concentrado | Actua en profundidad sobre la fibra capilar | Refuerza el resultado de la linea | AA118: Tratamiento intensivo | AC118: Aplicar mechon por mechon despues del champu, dejar actuar de 3 a 5 minutos y enjuagar bien. | AD118: Extrato de quina rosa | AE118: Extracto de quina rosa | AH118: mascara-de-tratamento-quina-rosa-900g.webp | AJ118: Cabello opaco, con frizz o sin vida | AK118: https://haskellcosmeticos.com.br/tratamentos-capilares/linha-quina-rosa-haskell/ | AL118: 2026-07-24 | AM118: =IF(ISBLANK(Q118),"",Q118*Parametros_PEN!$B$2) | AN118: =IF(ISBLANK(Q118),"",Q118*Parametros_PEN!$B$2*(1+Parametros_PEN!$B$3)) | AO118: =IF(ISBLANK(R118),"",R118*Parametros_PEN!$B$2) | AP118: =IF(ISBLANK(R118),"",R118*Parametros_PEN!$B$2*(1+Parametros_PEN!$B$3))
A119: HSK-0118 | B119: espuma-forma-rizos-se-curve-180-ml | D119: Haskell | E119: Mousse Forma Cachos Se Curve 180ml | F119: Espuma forma rizos Se Curve 180 ml | G119: Se Curve | H119: Tratamentos Capilares | I119: Tratamientos capilares | J119: Cuidado para cabelo cacheado, crespo e ondulado | K119: Cuidado para cabello rizado, ondulado y afro | L119: Mousse | M119: Espuma modeladora | N119: 180 ml | O119: 180 | P119: ml | Q119: 59.9 | S119: =IF(ISBLANK(R119),0,IFERROR((Q119-R119)/Q119,0)) | T119: =R119<>"" | U119: =TRUE() | W119: Espuma modeladora de la linea Se Curve: nutre y define las curvas naturales del cabello, desde ondas hasta rizos muy cerrados. | Y119: Define la forma natural del cabello | Controla el volumen | No apelmaza | AA119: Modelador | AC119: Aplicar sobre el cabello humedo, distribuir con las manos y dejar secar al natural o con difusor. | AD119: Rosa mosqueta | Manteiga de karite | Manteiga de cupuacu | Manteiga de murumuru | Colageno vegetal | Cana-de-acucar | Goma de tapioca | Arginina | Babosa | AE119: Rosa mosqueta | Manteca de karite | Manteca de cupuazu | Manteca de murumuru | Colageno vegetal | Cana de azucar | Goma de tapioca | Arginina | Aloe vera | AH119: mousse-se-curve-180ml.webp | AI119: mousse-se-curve-180ml_02.webp | AJ119: Cabello ondulado, rizado o afro (curvaturas 2A a 4C) | AK119: https://haskellcosmeticos.com.br/tratamentos-capilares/se-curve/ | AL119: 2026-07-24 | AM119: =IF(ISBLANK(Q119),"",Q119*Parametros_PEN!$B$2) | AN119: =IF(ISBLANK(Q119),"",Q119*Parametros_PEN!$B$2*(1+Parametros_PEN!$B$3)) | AO119: =IF(ISBLANK(R119),"",R119*Parametros_PEN!$B$2) | AP119: =IF(ISBLANK(R119),"",R119*Parametros_PEN!$B$2*(1+Parametros_PEN!$B$3))
A120: HSK-0119 | B120: mascarilla-3-mantecas-se-curve-500-g | D120: Haskell | E120: Mascara 3 Manteigas Se Curve 500g | F120: Mascarilla 3 mantecas Se Curve 500 g | G120: Se Curve | H120: Tratamentos Capilares | I120: Tratamientos capilares | J120: Cuidado para cabelo cacheado, crespo e ondulado | K120: Cuidado para cabello rizado, ondulado y afro | L120: Mascara de Tratamento | M120: Mascarilla de tratamiento | N120: 500 g | O120: 500 | P120: g | Q120: 81.9 | S120: =IF(ISBLANK(R120),0,IFERROR((Q120-R120)/Q120,0)) | T120: =R120<>"" | U120: =TRUE() | W120: Mascarilla de tratamiento concentrada de la linea Se Curve, de uso posterior al champu: nutre y define las curvas naturales del cabello, desde ondas hasta rizos muy cerrados. | Y120: Tratamiento concentrado | Actua en profundidad sobre la fibra capilar | Refuerza el resultado de la linea | AA120: Tratamiento intensivo | AC120: Aplicar mechon por mechon despues del champu, dejar actuar de 3 a 5 minutos y enjuagar bien. | AD120: Rosa mosqueta | Manteiga de karite | Manteiga de cupuacu | Manteiga de murumuru | Colageno vegetal | Cana-de-acucar | Goma de tapioca | Arginina | Babosa | AE120: Rosa mosqueta | Manteca de karite | Manteca de cupuazu | Manteca de murumuru | Colageno vegetal | Cana de azucar | Goma de tapioca | Arginina | Aloe vera | AH120: mascara-3-manteigas-se-curve-500g.webp | AJ120: Cabello ondulado, rizado o afro (curvaturas 2A a 4C) | AK120: https://haskellcosmeticos.com.br/tratamentos-capilares/se-curve/ | AL120: 2026-07-24 | AM120: =IF(ISBLANK(Q120),"",Q120*Parametros_PEN!$B$2) | AN120: =IF(ISBLANK(Q120),"",Q120*Parametros_PEN!$B$2*(1+Parametros_PEN!$B$3)) | AO120: =IF(ISBLANK(R120),"",R120*Parametros_PEN!$B$2) | AP120: =IF(ISBLANK(R120),"",R120*Parametros_PEN!$B$2*(1+Parametros_PEN!$B$3))
A121: HSK-0120 | B121: champu-se-curve-500-ml | D121: Haskell | E121: Shampoo Se Curve 500ml | F121: Champu Se Curve 500 ml | G121: Se Curve | H121: Tratamentos Capilares | I121: Tratamientos capilares | J121: Cuidado para cabelo cacheado, crespo e ondulado | K121: Cuidado para cabello rizado, ondulado y afro | L121: Shampoo | M121: Champu | N121: 500 ml | O121: 500 | P121: ml | Q121: 76.9 | S121: =IF(ISBLANK(R121),0,IFERROR((Q121-R121)/Q121,0)) | T121: =R121<>"" | U121: =TRUE() | W121: Champu de limpieza suave de la linea Se Curve, que prepara el cabello para el tratamiento: nutre y define las curvas naturales del cabello, desde ondas hasta rizos muy cerrados. | Y121: Limpieza suave sin resecar | Prepara el cabello para el resto de la rutina | Respeta el equilibrio del cuero cabelludo | AA121: Limpiador suave | AC121: Aplicar sobre el cabello mojado, masajear el cuero cabelludo con movimientos suaves y enjuagar bien. | AD121: Rosa mosqueta | Manteiga de karite | Manteiga de cupuacu | Manteiga de murumuru | Colageno vegetal | Cana-de-acucar | Goma de tapioca | Arginina | Babosa | AE121: Rosa mosqueta | Manteca de karite | Manteca de cupuazu | Manteca de murumuru | Colageno vegetal | Cana de azucar | Goma de tapioca | Arginina | Aloe vera | AH121: shampoo-se-curve-500ml.webp | AJ121: Cabello ondulado, rizado o afro (curvaturas 2A a 4C) | AK121: https://haskellcosmeticos.com.br/tratamentos-capilares/se-curve/ | AL121: 2026-07-24 | AM121: =IF(ISBLANK(Q121),"",Q121*Parametros_PEN!$B$2) | AN121: =IF(ISBLANK(Q121),"",Q121*Parametros_PEN!$B$2*(1+Parametros_PEN!$B$3)) | AO121: =IF(ISBLANK(R121),"",R121*Parametros_PEN!$B$2) | AP121: =IF(ISBLANK(R121),"",R121*Parametros_PEN!$B$2*(1+Parametros_PEN!$B$3))
A122: HSK-0121 | B122: acondicionador-se-curve-500-ml | D122: Haskell | E122: Condicionador Se Curve 500ml | F122: Acondicionador Se Curve 500 ml | G122: Se Curve | H122: Tratamentos Capilares | I122: Tratamientos capilares | J122: Cuidado para cabelo cacheado, crespo e ondulado | K122: Cuidado para cabello rizado, ondulado y afro | L122: Condicionador | M122: Acondicionador | N122: 500 ml | O122: 500 | P122: ml | Q122: 76.9 | S122: =IF(ISBLANK(R122),0,IFERROR((Q122-R122)/Q122,0)) | T122: =R122<>"" | U122: =TRUE() | W122: Acondicionador de la linea Se Curve que facilita el desenredado y sella la cuticula: nutre y define las curvas naturales del cabello, desde ondas hasta rizos muy cerrados. | Y122: Facilita el desenredado | Sella la cuticula | Aporta suavidad y brillo | AA122: Acondicionador | AC122: Aplicar en el largo y las puntas del cabello despues del champu, dejar actuar unos minutos y enjuagar. | AD122: Rosa mosqueta | Manteiga de karite | Manteiga de cupuacu | Manteiga de murumuru | Colageno vegetal | Cana-de-acucar | Goma de tapioca | Arginina | Babosa | AE122: Rosa mosqueta | Manteca de karite | Manteca de cupuazu | Manteca de murumuru | Colageno vegetal | Cana de azucar | Goma de tapioca | Arginina | Aloe vera | AH122: condicionador-se-curve-500ml.webp | AJ122: Cabello ondulado, rizado o afro (curvaturas 2A a 4C) | AK122: https://haskellcosmeticos.com.br/tratamentos-capilares/se-curve/ | AL122: 2026-07-24 | AM122: =IF(ISBLANK(Q122),"",Q122*Parametros_PEN!$B$2) | AN122: =IF(ISBLANK(Q122),"",Q122*Parametros_PEN!$B$2*(1+Parametros_PEN!$B$3)) | AO122: =IF(ISBLANK(R122),"",R122*Parametros_PEN!$B$2) | AP122: =IF(ISBLANK(R122),"",R122*Parametros_PEN!$B$2*(1+Parametros_PEN!$B$3))
A123: HSK-0122 | B123: crema-de-peinar-se-curve-500-g | D123: Haskell | E123: Creme de Pentear Se Curve 500g | F123: Crema de peinar Se Curve 500 g | G123: Se Curve | H123: Tratamentos Capilares | I123: Tratamientos capilares | J123: Cuidado para cabelo cacheado, crespo e ondulado | K123: Cuidado para cabello rizado, ondulado y afro | L123: Creme | M123: Crema | N123: 500 g | O123: 500 | P123: g | Q123: 92.9 | S123: =IF(ISBLANK(R123),0,IFERROR((Q123-R123)/Q123,0)) | T123: =R123<>"" | U123: =TRUE() | W123: Crema de la linea Se Curve: nutre y define las curvas naturales del cabello, desde ondas hasta rizos muy cerrados. | Y123: Facilita el peinado | Hidrata y da forma segun el uso | AA123: Multifuncion | AC123: Aplicar sobre el cabello humedo o seco, segun la necesidad, y finalizar como se prefiera. | AD123: Rosa mosqueta | Manteiga de karite | Manteiga de cupuacu | Manteiga de murumuru | Colageno vegetal | Cana-de-acucar | Goma de tapioca | Arginina | Babosa | AE123: Rosa mosqueta | Manteca de karite | Manteca de cupuazu | Manteca de murumuru | Colageno vegetal | Cana de azucar | Goma de tapioca | Arginina | Aloe vera | AH123: creme-de-pentear-se-curve-500g.webp | AJ123: Cabello ondulado, rizado o afro (curvaturas 2A a 4C) | AK123: https://haskellcosmeticos.com.br/tratamentos-capilares/se-curve/ | AL123: 2026-07-24 | AM123: =IF(ISBLANK(Q123),"",Q123*Parametros_PEN!$B$2) | AN123: =IF(ISBLANK(Q123),"",Q123*Parametros_PEN!$B$2*(1+Parametros_PEN!$B$3)) | AO123: =IF(ISBLANK(R123),"",R123*Parametros_PEN!$B$2) | AP123: =IF(ISBLANK(R123),"",R123*Parametros_PEN!$B$2*(1+Parametros_PEN!$B$3))
A124: HSK-0123 | B124: tonico-transicion-capilar-se-curve-200-ml | D124: Haskell | E124: Tonico Transicao Capilar Se Curve 200ml | F124: Tonico transicion capilar Se Curve 200 ml | G124: Se Curve | H124: Tratamentos Capilares | I124: Tratamientos capilares | J124: Cuidado para cabelo cacheado, crespo e ondulado | K124: Cuidado para cabello rizado, ondulado y afro | L124: Tonico | M124: Tonico capilar | N124: 200 ml | O124: 200 | P124: ml | Q124: 56.9 | S124: =IF(ISBLANK(R124),0,IFERROR((Q124-R124)/Q124,0)) | T124: =R124<>"" | U124: =TRUE() | W124: Tonico capilar de la linea Se Curve, de uso directo sobre el cuero cabelludo: nutre y define las curvas naturales del cabello, desde ondas hasta rizos muy cerrados. | Y124: Estimula el cuero cabelludo | Refuerza la raiz del cabello | AA124: Tonico capilar | AC124: Aplicar directamente sobre el cuero cabelludo limpio y masajear suavemente. No es necesario enjuagar. | AD124: Rosa mosqueta | Manteiga de karite | Manteiga de cupuacu | Manteiga de murumuru | Colageno vegetal | Cana-de-acucar | Goma de tapioca | Arginina | Babosa | AE124: Rosa mosqueta | Manteca de karite | Manteca de cupuazu | Manteca de murumuru | Colageno vegetal | Cana de azucar | Goma de tapioca | Arginina | Aloe vera | AH124: tonico-transicao-capilar-se-curve-200ml.webp | AJ124: Cabello ondulado, rizado o afro (curvaturas 2A a 4C) | AK124: https://haskellcosmeticos.com.br/tratamentos-capilares/se-curve/ | AL124: 2026-07-24 | AM124: =IF(ISBLANK(Q124),"",Q124*Parametros_PEN!$B$2) | AN124: =IF(ISBLANK(Q124),"",Q124*Parametros_PEN!$B$2*(1+Parametros_PEN!$B$3)) | AO124: =IF(ISBLANK(R124),"",R124*Parametros_PEN!$B$2) | AP124: =IF(ISBLANK(R124),"",R124*Parametros_PEN!$B$2*(1+Parametros_PEN!$B$3))
A125: HSK-0124 | B125: curva-cola-se-curve-500-g | D125: Haskell | E125: Curva & Cola Se Curve 500g | F125: Curva & Cola Se Curve 500 g | G125: Se Curve | H125: Tratamentos Capilares | I125: Tratamientos capilares | J125: Cuidado para cabelo cacheado, crespo e ondulado | K125: Cuidado para cabello rizado, ondulado y afro | L125: Goma | M125: Gel texturizador | N125: 500 g | O125: 500 | P125: g | Q125: 92.9 | S125: =IF(ISBLANK(R125),0,IFERROR((Q125-R125)/Q125,0)) | T125: =R125<>"" | U125: =TRUE() | W125: Gel texturizador de la linea Se Curve: nutre y define las curvas naturales del cabello, desde ondas hasta rizos muy cerrados. | Y125: Define y fija sin apelmazar | Controla el frizz | Textura maleable | AA125: Texturizador | AC125: Aplicar sobre el cabello humedo, distribuir mechon por mechon para definir la forma deseada. | AD125: Rosa mosqueta | Manteiga de karite | Manteiga de cupuacu | Manteiga de murumuru | Colageno vegetal | Cana-de-acucar | Goma de tapioca | Arginina | Babosa | AE125: Rosa mosqueta | Manteca de karite | Manteca de cupuazu | Manteca de murumuru | Colageno vegetal | Cana de azucar | Goma de tapioca | Arginina | Aloe vera | AH125: curva-cola-se-curve-500g.webp | AJ125: Cabello ondulado, rizado o afro (curvaturas 2A a 4C) | AK125: https://haskellcosmeticos.com.br/tratamentos-capilares/se-curve/ | AL125: 2026-07-24 | AM125: =IF(ISBLANK(Q125),"",Q125*Parametros_PEN!$B$2) | AN125: =IF(ISBLANK(Q125),"",Q125*Parametros_PEN!$B$2*(1+Parametros_PEN!$B$3)) | AO125: =IF(ISBLANK(R125),"",R125*Parametros_PEN!$B$2) | AP125: =IF(ISBLANK(R125),"",R125*Parametros_PEN!$B$2*(1+Parametros_PEN!$B$3))
...

Sheet Parametros_PEN
A1: Parametro | B1: Valor
A2: Tipo de cambio (soles PEN por 1 real BRL) | B2: 0.67
A3: Margen sobre el precio convertido para fijar el PVP en Peru | B3: 0.25
A5: Formula aplicada
A6: precio_pen = precio_brl x tipo_cambio
A7: pvp_peru_pen = precio_pen x (1 + margen)
A9: Nota
A10: Celdas B2 y B3 son los unicos valores editables. El resto del catalogo (hoja Productos) usa formulas que apuntan a estas dos celdas: si se actualiza el tipo de cambio o el margen aca, todos los precios en soles y el PVP se recalculan automaticamente en toda la hoja Productos.

Sheet Categorias_Lineas
A1: categoria_original_pt | B1: categoria_es | C1: linea | D1: subcategoria_original_pt | E1: subcategoria_es | F1: cantidad_productos_en_muestra
A2: Tratamentos Capilares | B2: Tratamientos capilares | C2: Acidificante | D2: Reconstrucao pos-quimica | E2: Reconstruccion post-quimica | F2: 3
A3: Tratamentos Capilares | B3: Tratamientos capilares | C3: Acidificante Matizadora | D3: Matizacao acida | E3: Matizacion acida para cabello rubio o canoso | F3: 3
A4: Tratamentos Capilares | B4: Tratamientos capilares | C4: Ametista Desamareladora | D4: Desamarelamento gradual | E4: Desamarillamiento gradual | F4: 4
A5: Tratamentos Capilares | B5: Tratamientos capilares | C5: Bananeira Pos-Quimica | D5: Reposicao de massa pos-quimica | E5: Reposicion de masa capilar post-quimica | F5: 8
A6: Tratamentos Capilares | B6: Tratamientos capilares | C6: Bendito Loiro | D6: Cabelos descoloridos | E6: Cabello decolorado | F6: 6
A7: Tratamentos Capilares | B7: Tratamientos capilares | C7: Cachos Sim! | D7: Cuidado de cachos | E7: Cuidado de rizos | F7: 4
A8: Tratamentos Capilares | B8: Tratamientos capilares | C8: Cavalo Forte | D8: Fortalecimento | E8: Fortalecimiento capilar | F8: 1
A9: Tratamentos Capilares | B9: Tratamientos capilares | C9: Cavalo Forte Hidra | D9: Hidratacao profunda | E9: Hidratacion profunda | F9: 7
A10: Tratamentos Capilares | B10: Tratamientos capilares | C10: Doce de Leite Vicosa | D10: Colecao corpo e cabelo perfumada | E10: Coleccion de cuidado corporal y capilar perfumada | F10: 3
A11: Tratamentos Capilares | B11: Tratamientos capilares | C11: Encorpa Cabelo | D11: Volume para cabelo fino | E11: Volumen para cabello fino | F11: 7
A12: Tratamentos Capilares | B12: Tratamientos capilares | C12: Frizz Cancelado | D12: Controle de frizz | E12: Control del frizz | F12: 3
A13: Tratamentos Capilares | B13: Tratamientos capilares | C13: Hidranutre | D13: Hidratacao e nutricao combinadas | E13: Hidratacion y nutricion combinadas | F13: 8
... A30: Tratamentos Capilares | B30: Tratamientos capilares | C30: Tutano Vegetal | D30: Forca e nutricao profunda | E30: Fuerza y nutricion profunda | F30: 7
E32: Total productos en la muestra: | F32: =SUM(F2:F30)

Sheet Notas_Metodologicas
A1: Fuente
A2: https://haskellcosmeticos.com.br/ — paginas publicas de linea dentro de Tratamentos Capilares (sin login, sin CAPTCHA evadido).
A4: Fecha de extraccion
A5: 2026-07-24
A7: Alcance de esta version
A8: 143 productos reales, en 29 lineas (todas las lineas de Tratamentos Capilares publicadas en el sitio al momento de la extraccion). Se excluyeron los KITS (combos de productos ya listados de forma individual) para no duplicar filas. En 2 lineas (Mandioca, Queratina & Provit B5) la pagina solo mostraba precio individual confirmado para 1 producto — el resto de los items mencionados en el texto de la linea no tenian precio individual visible en la grilla (solo en kits), por lo que no se incluyeron para no inventar precios.
A10: Como se obtuvo
A11: Navegacion directa a las paginas publicas de cada una de las 29 lineas y lectura del texto renderizado (nombre, tamano, precio regular y de oferta en BRL, activos principales). No se uso el exportador Playwright del paquete original; para el catalogo 100% completo (incluyendo kits, coloracion y variantes no publicadas en paginas de linea) corresponde ejecutar 'npm run scrape' del exportador ya entregado.
A13: Redaccion de descripciones, beneficios y modo de uso
A14: IMPORTANTE: a diferencia de los primeros 20 productos (redactados a mano, ficha por ficha), los 123 productos agregados en esta version usan una redaccion generada a partir de plantillas propias por tipo de producto (champu, acondicionador, mascarilla, leave-in, tonico, etc.) combinadas con el proposito de cada linea. Esto se hizo asi para poder cubrir el catalogo completo en un tiempo razonable. El contenido es original (no es traduccion literal de los textos de marketing del sitio) y describe funciones genericas y reales del tipo de producto, pero es menos especifico que si cada ficha se hubiera redactado individualmente. Los activos y precios si son especificos de cada linea/producto.
A16: Precios
A17: Todos los precios son los publicados en BRL (real brasileno) al momento de la extraccion. Cuando la pagina de linea mostraba precio de oferta ademas del regular, se cargaron ambos (precio_oferta_brl); si no se mostraba oferta, la columna queda vacia y en_oferta = FALSO. No se inventaron descuentos.
... A41: 1) Revisar esta version ampliada (143 productos, 29 lineas). 2) Si se necesita redaccion ficha por ficha (no por plantilla) para las 123 lineas agregadas, o se necesitan los kits, avisar para una pasada adicional. 3) Ejecutar el exportador completo (npm run scrape) para INCI, imagenes y coloracion. 4) Cargar el resultado en el esquema Postgres adjunto (esquema_postgres.sql). 5) Vincular cada 'sku' resultante con CatalogLine.sku del backend de la plataforma comercial.
